Workbook

Sheet 📦 Inventario Maestro
A1: MAX TECHNOLOGY STORE — INVENTARIO FÍSICO Y CATÁLOGO DE PRECIOS
A2: 🟡 Columna 'Stock Físico Actual': escribe la cantidad en taller | 🟢 Precios WhatsApp, MercadoLibre, Facebook y Utilidades calculados con fórmulas 100% compatibles
A3: SKU | B3: Producto / Descripción Comercial | C3: Categoría | D3: Marca | E3: Modelo / No. Parte | F3: Color | G3: Código de Barras (EAN/UPC) | H3: Estado | I3: Disponibilidad | J3: Stock Físico Actual | K3: Histórico Comprado | L3: Ubicación Física | M3: Costo Total Unitario (COP) | N3: Margen Deseado | O3: Precio WhatsApp / Directo (COP) | P3: Comisión ML | Q3: Precio MercadoLibre (COP) | R3: Precio Facebook (COP) | S3: Utilidad Directa (COP) | T3: Margen Real Directo | U3: Garantía Oficial | V3: Ruta Foto Local | W3: Beneficio Principal (Cliente) | X3: Notas / Observaciones
A4: MTS-0001 | B4: Kit Solar Renogy 100W 12V Monocristalino + Controlador PWM 30A Wanderer | C4: Energía Solar y Electrónica | D4: Renogy | E4: RNG-KIT-STARTER100D-WND30 | F4: Negro | G4: 810057240123 | H4: NUEVO | I4: 🟢 En Stock | J4: 1 | K4: 1 | L4: Bodega Principal - Estante A | M4: 580115 | N4: 0.30022232 | O4: =IF(N4<1, ROUNDUP(M4/(1-N4), -3), M4) | P4: 0.16 | Q4: =IF((1-N4-P4)>0, ROUNDUP((M4+IF(O4>=90000,20000,0))/(1-N4-P4), -3), O4) | R4: =O4 | S4: =O4-M4 | T4: =IF(O4>0, (O4-M4)/O4, 0) | U4: 12 Meses | V4: IMAGENES DE PRODUCTOS/Panel solar.jpg | W4: Kit solar completo con panel monocristalino de 100W y controlador inteligente de 30A. Te da energía limpia y autónoma en fincas, casas de campo o vehículos recreativos para iluminar, cargar celulares y alimentar equipos. | X4: Kit sellado de fábrica.
A5: MTS-0002 | B5: Lector Escáner de Código de Barras Zebra DS9208 Digital 1D y 2D Manos Libres USB | C5: Puntos de Venta y POS | D5: Zebra | E5: DS9208-SR4NNU21Z | F5: Negro | H5: REMANUFACTURADO | I5: 🟢 En Stock | J5: 2 | K5: 2 | L5: Vitrina Principal - POS | M5: 131293 | N5: 0.20428003 | O5: =IF(N5<1, ROUNDUP(M5/(1-N5), -3), M5) | P5: 0.16 | Q5: =IF((1-N5-P5)>0, ROUNDUP((M5+IF(O5>=90000,20000,0))/(1-N5-P5), -3), O5) | R5: =O5 | S5: =O5-M5 | T5: =IF(O5>0, (O5-M5)/O5, 0) | U5: 3 Meses de Garantía | V5: IMAGENES DE PRODUCTOS/ZEBRA DS9208.jpg | W5: Lector digital de alta velocidad manos libres para puntos de venta, supermercados y farmacias. Lee códigos de barras tradicionales (1D) y códigos QR / 2D tanto impresos en papel como directamente desde la pantalla del celular. Conexión USB inmediata plug & play.
A6: MTS-0003 | B6: Mouse Inalámbrico Logitech M170 Óptico 1000 DPI Negro | C6: Periféricos y Accesorios | D6: Logitech | E6: 910-004425 | F6: Negro | G6: 097855124180 | H6: NUEVO | I6: ⚪ Agotado | J6: 0 | K6: 0 | L6: Vitrina Accesorios | M6: 39705 | N6: 0.11764706 | O6: =IF(N6<1, ROUNDUP(M6/(1-N6), -3), M6) | P6: 0.16 | Q6: =IF((1-N6-P6)>0, ROUNDUP((M6+IF(O6>=90000,20000,0))/(1-N6-P6), -3), O6) | R6: =O6 | S6: =O6-M6 | T6: =IF(O6>0, (O6-M6)/O6, 0) | U6: 12 Meses Logitech | V6: IMAGENES DE PRODUCTOS/MOUSE M170 NEGRO LOGITECH.jpg | W6: Mouse inalámbrico compacto, supercómodo y confiable. Se conecta con un receptor USB miniatura con alcance de hasta 10 metros y su batería dura hasta 1 año completo con una sola pila.
A7: MTS-0004 | B7: Router Mercusys MR30G AC1200 Gigabit Dual-Band Wi-Fi (4 Antenas 5dBi) | C7: Redes y Conectividad | D7: Mercusys | E7: MR30G | F7: Negro | G7: 849439000614 | H7: NUEVO | I7: ⚪ Agotado | J7: 0 | K7: 0 | L7: Estante C - Redes | M7: 90586 | N7: 0.2122888 | O7: =IF(N7<1, ROUNDUP(M7/(1-N7), -3), M7) | P7: 0.16 | Q7: =IF((1-N7-P7)>0, ROUNDUP((M7+IF(O7>=90000,20000,0))/(1-N7-P7), -3), O7) | R7: =O7 | S7: =O7-M7 | T7: =IF(O7>0, (O7-M7)/O7, 0) | U7: 24 Meses (2 Años) | V7: IMAGENES DE PRODUCTOS/Router C1200.jpeg | W7: Router de alta velocidad con puertos Gigabit para aprovechar al 100% planes de fibra óptica de 100 a 300 Megas. Tiene 4 antenas de buen alcance y transmite en dos bandas (2.4GHz y 5GHz) para que navegues sin cortes.
A8: MTS-0005 | B8: Combo Teclado y Mouse Logitech MK120 Alámbrico USB Español Antiderrames | C8: Periféricos y Accesorios | D8: Logitech | E8: 920-004428 | F8: Negro | G8: 097855088802 | H8: NUEVO | I8: 🟢 En Stock | J8: 1 | K8: 1 | L8: Caja 2 - Periféricos | M8: 59921 | N8: 0.14397349 | O8: =IF(N8<1, ROUNDUP(M8/(1-N8), -3), M8) | P8: 0.16 | Q8: =IF((1-N8-P8)>0, ROUNDUP((M8+IF(O8>=90000,20000,0))/(1-N8-P8), -3), O8) | R8: =O8 | S8: =O8-M8 | T8: =IF(O8>0, (O8-M8)/O8, 0) | U8: 36 Meses (3 Años Logitech) | V8: IMAGENES DE PRODUCTOS/combo teclado + mouse mk120.webp | W8: El combo de oficina más duradero y vendido. Teclado con letra Ñ, teclas suaves y silenciosas que no se borran con el uso, resistente a salpicaduras de líquidos, y mouse óptico muy preciso y cómodo. Cuenta con 3 años de garantía oficial.
A9: MTS-0006 | B9: Teclado Logitech K120 Alámbrico USB Español Negro Resistente | C9: Periféricos y Accesorios | D9: Logitech | E9: 920-004422 | F9: Negro | G9: 097855088741 | H9: NUEVO | I9: 🟢 En Stock | J9: 1 | K9: 1 | L9: Caja 2 - Periféricos | M9: 43435 | N9: 0.21025837 | O9: =IF(N9<1, ROUNDUP(M9/(1-N9), -3), M9) | P9: 0.16 | Q9: =IF((1-N9-P9)>0, ROUNDUP((M9+IF(O9>=90000,20000,0))/(1-N9-P9), -3), O9) | R9: =O9 | S9: =O9-M9 | T9: =IF(O9>0, (O9-M9)/O9, 0) | U9: 24 Meses (2 Años) | V9: IMAGENES DE PRODUCTOS/teclado usb mk120.webp | W9: Teclado de tamaño completo con teclado numérico y distribución en español. Fabricado para soportar derrames de líquidos y años de trabajo continuo en oficina o casa sin fallar.
A10: MTS-0007 | B10: Mouse Óptico Logitech B100 USB 800 DPI con Cable Negro | C10: Periféricos y Accesorios | D10: Logitech | E10: 910-001439 | F10: Negro | G10: 097855014399 | H10: NUEVO | I10: 🟢 En Stock | J10: 1 | K10: 1 | L10: Caja 2 - Periféricos | M10: 16180 | N10: 0.35277411 | O10: =IF(N10<1, ROUNDUP(M10/(1-N10), -3), M10) | P10: 0.16 | Q10: =IF((1-N10-P10)>0, ROUNDUP((M10+IF(O10>=90000,20000,0))/(1-N10-P10), -3), O10) | R10: =O10 | S10: =O10-M10 | T10: =IF(O10>0, (O10-M10)/O10, 0) | U10: 36 Meses (3 Años) | V10: IMAGENES DE PRODUCTOS/Mouse USB B100 Logitech.webp | W10: Mouse con cable USB clásico de Logitech, superpreciso, cómodo para cualquier tamaño de mano y con 3 años de garantía oficial.
A11: MTS-0008 | B11: Cargador para Portátil Lenovo Yoga 65W 20V 3.25A Conector USB PIN | C11: Cargadores y Fuentes | D11: Marinansa | E11: USB-PIN-65W | F11: Negro | G11: 202404GW140042 | H11: NUEVO | I11: 🟢 En Stock | J11: 1 | K11: 1 | L11: Caja 1 - Cargadores | M11: 45000 | N11: 0.2499875 | O11: =IF(N11<1, ROUNDUP(M11/(1-N11), -3), M11) | P11: 0.16 | Q11: =IF((1-N11-P11)>0, ROUNDUP((M11+IF(O11>=90000,20000,0))/(1-N11-P11), -3), O11) | R11: =O11 | S11: =O11-M11 | T11: =IF(O11>0, (O11-M11)/O11, 0) | U11: 6 Meses de Garantía | V11: IMAGENES DE PRODUCTOS/Cargador UBS PIN 20v 3.25A.PNG | W11: Cargador de 65W (20V a 3.25A) con conector rectangular amarillo USB PIN para laptops Lenovo ThinkPad, IdeaPad y serie Yoga. Incluye su cable de poder.
A12: MTS-0009 | B12: Mouse Genius DX-101 Alámbrico Óptico USB 1000 DPI Negro | C12: Periféricos y Accesorios | D12: Genius | E12: 31010026400 | F12: Negro | G12: 4710268254218 | H12: NUEVO | I12: 🟢 En Stock | J12: 1 | K12: 1 | L12: Caja 2 - Periféricos | M12: 10948 | N12: 0.27008467 | O12: =IF(N12<1, ROUNDUP(M12/(1-N12), -3), M12) | P12: 0.16 | Q12: =IF((1-N12-P12)>0, ROUNDUP((M12+IF(O12>=90000,20000,0))/(1-N12-P12), -3), O12) | R12: =O12 | S12: =O12-M12 | T12: =IF(O12>0, (O12-M12)/O12, 0) | U12: 12 Meses | V12: IMAGENES DE PRODUCTOS/MOUSE DX-101.webp | W12: Mouse óptico de cable USB, sencillo, ergonómico y muy económico para uso diario en el hogar o trabajo.
A13: MTS-0010 | B13: Funda Protectora Doble Faz para Portátil 14" - 15.6" Neopreno | C13: Accesorios y Fundas | D13: Genérica | E13: JRG01 | F13: Negro / Rojo | H13: NUEVO | I13: 🟢 En Stock | J13: 3 | K13: 3 | L13: Vitrina Accesorios | M13: 12000 | N13: 0.15 | O13: =IF(N13<1, ROUNDUP(M13/(1-N13), -3), M13) | P13: 0.16 | Q13: =IF((1-N13-P13)>0, ROUNDUP((M13+IF(O13>=90000,20000,0))/(1-N13-P13), -3), O13) | R13: =O13 | S13: =O13-M13 | T13: =IF(O13>0, (O13-M13)/O13, 0) | U13: 1 Mes | V13: IMAGENES DE PRODUCTOS/FUNDA PARA PORTATIL.webp | W13: Funda en neopreno acolchado reversible (negro por un lado y rojo por el otro). Protege tu computador portátil de rayones, golpes leves y polvo dentro de tu morral o bolso.
A14: MTS-0011 | B14: Tinta Genérica Epson 524 Gihonclock Negra 127ml (G-524) | C14: Tintas y Suministros | D14: Gihonclock | E14: G-524 | F14: Negro | G14: 8016013040522 | H14: NUEVO | I14: 🟢 En Stock | J14: 2 | K14: 2 | L14: Estante Tintas - Nivel 1 | M14: 25000 | N14: 0.4444321 | O14: =IF(N14<1, ROUNDUP(M14/(1-N14), -3), M14) | P14: 0.16 | Q14: =IF((1-N14-P14)>0, ROUNDUP((M14+IF(O14>=90000,20000,0))/(1-N14-P14), -3), O14) | R14: =O14 | S14: =O14-M14 | T14: =IF(O14>0, (O14-M14)/O14, 0) | U14: Garantía de Calidad de Impresión | V14: IMAGENES DE PRODUCTOS/TINTA G-524 NEGRA.PNG | W14: Botella de tinta genérica de 127ml de alta pigmentación para impresoras Epson EcoTank serie L. Excelente nitidez en textos y documentos. | X14: Presentación de 127ml.
A15: MTS-0012 | B15: Botella de Tinta Original Canon GI-11 Magenta | C15: Tintas y Suministros | D15: Canon | E15: GI-11M | F15: Magenta | G15: 013803328400 | H15: NUEVO | I15: 🟢 En Stock | J15: 1 | K15: 1 | L15: Estante Tintas - Nivel 2 | M15: 30000 | N15: 0.399988 | O15: =IF(N15<1, ROUNDUP(M15/(1-N15), -3), M15) | P15: 0.16 | Q15: =IF((1-N15-P15)>0, ROUNDUP((M15+IF(O15>=90000,20000,0))/(1-N15-P15), -3), O15) | R15: =O15 | S15: =O15-M15 | T15: =IF(O15>0, (O15-M15)/O15, 0) | U15: 100% Original Canon | V15: IMAGENES DE PRODUCTOS/TINTA 11M CANON.jpg | W15: Tinta 100% original Canon GI-11 color Magenta para impresoras de tanque continuo Canon MegaTank (G2160, G3160, etc.). Colores vivos y duraderos sin tapar los cabezales. | X15: Botella original sellada.
A16: MTS-0013 | B16: Botella de Tinta Original Canon GI-11 Cyan | C16: Tintas y Suministros | D16: Canon | E16: GI-11C | F16: Cyan | G16: 013803328394 | H16: NUEVO | I16: 🟢 En Stock | J16: 1 | K16: 1 | L16: Estante Tintas - Nivel 2 | M16: 30000 | N16: 0.399988 | O16: =IF(N16<1, ROUNDUP(M16/(1-N16), -3), M16) | P16: 0.16 | Q16: =IF((1-N16-P16)>0, ROUNDUP((M16+IF(O16>=90000,20000,0))/(1-N16-P16), -3), O16) | R16: =O16 | S16: =O16-M16 | T16: =IF(O16>0, (O16-M16)/O16, 0) | U16: 100% Original Canon | V16: IMAGENES DE PRODUCTOS/TINTA 11C CANON.jpg | W16: Tinta original Canon GI-11 color Cyan para impresoras MegaTank. Máxima fidelidad en impresiones a color. | X16: Original sellada.
A17: MTS-0014 | B17: Botella de Tinta Original Canon GI-11 Amarillo | C17: Tintas y Suministros | D17: Canon | E17: GI-11Y | F17: Amarillo | G17: 013803328417 | H17: NUEVO | I17: 🟢 En Stock | J17: 1 | K17: 1 | L17: Estante Tintas - Nivel 2 | M17: 30000 | N17: 0.399988 | O17: =IF(N17<1, ROUNDUP(M17/(1-N17), -3), M17) | P17: 0.16 | Q17: =IF((1-N17-P17)>0, ROUNDUP((M17+IF(O17>=90000,20000,0))/(1-N17-P17), -3), O17) | R17: =O17 | S17: =O17-M17 | T17: =IF(O17>0, (O17-M17)/O17, 0) | U17: 100% Original Canon | V17: IMAGENES DE PRODUCTOS/TINTA 11Y CANON.jpg | W17: Tinta original Canon GI-11 color Amarillo para impresoras MegaTank. | X17: Original sellada.
A18: MTS-0015 | B18: Botella de Tinta Original Canon GI-190 Amarillo | C18: Tintas y Suministros | D18: Canon | E18: GI-190Y | F18: Amarillo | G18: 013803268232 | H18: NUEVO | I18: 🟢 En Stock | J18: 1 | K18: 1 | L18: Estante Tintas - Nivel 2 | M18: 20000 | N18: 0.33331111 | O18: =IF(N18<1, ROUNDUP(M18/(1-N18), -3), M18) | P18: 0.16 | Q18: =IF((1-N18-P18)>0, ROUNDUP((M18+IF(O18>=90000,20000,0))/(1-N18-P18), -3), O18) | R18: =O18 | S18: =O18-M18 | T18: =IF(O18>0, (O18-M18)/O18, 0) | U18: 100% Original Canon | V18: IMAGENES DE PRODUCTOS/TINTA CANON GI-190 A.jpg | W18: Tinta original Canon GI-190 Amarilla para impresoras Canon serie G (G2100, G3100, G4100, G2110, G3110). | X18: Original Canon.
A19: MTS-0016 | B19: Botella de Tinta Original Canon GI-190 Magenta | C19: Tintas y Suministros | D19: Canon | E19: GI-190M | F19: Magenta | G19: 013803268225 | H19: NUEVO | I19: 🟢 En Stock | J19: 1 | K19: 1 | L19: Estante Tintas - Nivel 2 | M19: 20000 | N19: 0.33331111 | O19: =IF(N19<1, ROUNDUP(M19/(1-N19), -3), M19) | P19: 0.16 | Q19: =IF((1-N19-P19)>0, ROUNDUP((M19+IF(O19>=90000,20000,0))/(1-N19-P19), -3), O19) | R19: =O19 | S19: =O19-M19 | T19: =IF(O19>0, (O19-M19)/O19, 0) | U19: 100% Original Canon | V19: IMAGENES DE PRODUCTOS/TINTA CANON GI-190 M.jpg | W19: Tinta original Canon GI-190 Magenta para impresoras de tanque continuo serie G. | X19: Original Canon.
A20: MTS-0017 | B20: Botella de Tinta Original Canon GI-190 Negro | C20: Tintas y Suministros | D20: Canon | E20: GI-190B | F20: Negro | G20: 013803268201 | H20: NUEVO | I20: 🟢 En Stock | J20: 1 | K20: 1 | L20: Estante Tintas - Nivel 2 | M20: 20000 | N20: 0.33331111 | O20: =IF(N20<1, ROUNDUP(M20/(1-N20), -3), M20) | P20: 0.16 | Q20: =IF((1-N20-P20)>0, ROUNDUP((M20+IF(O20>=90000,20000,0))/(1-N20-P20), -3), O20) | R20: =O20 | S20: =O20-M20 | T20: =IF(O20>0, (O20-M20)/O20, 0) | U20: 100% Original Canon | V20: IMAGENES DE PRODUCTOS/TINTA CANON GI-190 N.jpg | W20: Tinta original Canon GI-190 Negra de alta capacidad para impresoras serie G. | X20: Original Canon.
A21: MTS-0018 | B21: Botella de Tinta Original HP GT52 Amarilla (M0H56AL) | C21: Tintas y Suministros | D21: HP | E21: GT52A / M0H56AL | F21: Amarillo | G21: 190780132562 | H21: NUEVO | I21: 🟢 En Stock | J21: 1 | K21: 1 | L21: Estante Tintas - Nivel 3 | M21: 20000 | N21: 0.33331111 | O21: =IF(N21<1, ROUNDUP(M21/(1-N21), -3), M21) | P21: 0.16 | Q21: =IF((1-N21-P21)>0, ROUNDUP((M21+IF(O21>=90000,20000,0))/(1-N21-P21), -3), O21) | R21: =O21 | S21: =O21-M21 | T21: =IF(O21>0, (O21-M21)/O21, 0) | U21: 100% Original HP | V21: IMAGENES DE PRODUCTOS/Tinta HP GT52 A.jpg | W21: Tinta original HP GT52 Amarilla para impresoras HP Ink Tank y Smart Tank (series 115, 315, 415, 515, 615). Rendimiento de hasta 8.000 páginas en color. | X21: Original HP.
A22: MTS-0019 | B22: Botella de Tinta Original HP GT52 Cian (M0H54AL) | C22: Tintas y Suministros | D22: HP | E22: GT52C / M0H54AL | F22: Cyan | G22: 190780132562 | H22: NUEVO | I22: 🟢 En Stock | J22: 1 | K22: 1 | L22: Estante Tintas - Nivel 3 | M22: 20000 | N22: 0.33331111 | O22: =IF(N22<1, ROUNDUP(M22/(1-N22), -3), M22) | P22: 0.16 | Q22: =IF((1-N22-P22)>0, ROUNDUP((M22+IF(O22>=90000,20000,0))/(1-N22-P22), -3), O22) | R22: =O22 | S22: =O22-M22 | T22: =IF(O22>0, (O22-M22)/O22, 0) | U22: 100% Original HP | V22: IMAGENES DE PRODUCTOS/Tinta HP GT52 C.png | W22: Tinta original HP GT52 color Cian para impresoras HP Ink Tank y Smart Tank. | X22: Original HP.
A23: MTS-0020 | B23: Botella de Tinta Original HP GT52 Magenta (M0H55AL) | C23: Tintas y Suministros | D23: HP | E23: GT52M / M0H55AL | F23: Magenta | G23: 190780132562 | H23: NUEVO | I23: 🟢 En Stock | J23: 1 | K23: 1 | L23: Estante Tintas - Nivel 3 | M23: 20000 | N23: 0.33331111 | O23: =IF(N23<1, ROUNDUP(M23/(1-N23), -3), M23) | P23: 0.16 | Q23: =IF((1-N23-P23)>0, ROUNDUP((M23+IF(O23>=90000,20000,0))/(1-N23-P23), -3), O23) | R23: =O23 | S23: =O23-M23 | T23: =IF(O23>0, (O23-M23)/O23, 0) | U23: 100% Original HP | V23: IMAGENES DE PRODUCTOS/Tinta HP GT52 M.jpg | W23: Tinta original HP GT52 color Magenta para impresoras HP Ink Tank y Smart Tank. | X23: Original HP.
A24: MTS-0021 | B24: Botella de Tinta Original HP GT53 Negra (1VV22AL) | C24: Tintas y Suministros | D24: HP | E24: GT53N / 1VV22AL | F24: Negro | G24: 190780132562 | H24: NUEVO | I24: 🟢 En Stock | J24: 1 | K24: 1 | L24: Estante Tintas - Nivel 3 | M24: 20000 | N24: 0.33331111 | O24: =IF(N24<1, ROUNDUP(M24/(1-N24), -3), M24) | P24: 0.16 | Q24: =IF((1-N24-P24)>0, ROUNDUP((M24+IF(O24>=90000,20000,0))/(1-N24-P24), -3), O24) | R24: =O24 | S24: =O24-M24 | T24: =IF(O24>0, (O24-M24)/O24, 0) | U24: 100% Original HP | V24: IMAGENES DE PRODUCTOS/Tinta HP GT53 N.jpg | W24: Tinta original HP GT53 Negra con fórmula pigmentada para textos negros ultranítidos y resistentes al agua. Rinde hasta 6.000 páginas. | X24: Original HP.
A25: MTS-0022 | B25: Botella de Tinta Original Epson T504 Cian (T504220-AL) | C25: Tintas y Suministros | D25: Epson | E25: T504220-AL | F25: Cyan | G25: 010343938755 | H25: NUEVO | I25: 🟢 En Stock | J25: 2 | K25: 1 | L25: Estante Tintas - Nivel 4 | M25: 20000 | N25: 0.33331111 | O25: =IF(N25<1, ROUNDUP(M25/(1-N25), -3), M25) | P25: 0.16 | Q25: =IF((1-N25-P25)>0, ROUNDUP((M25+IF(O25>=90000,20000,0))/(1-N25-P25), -3), O25) | R25: =O25 | S25: =O25-M25 | T25: =IF(O25>0, (O25-M25)/O25, 0) | U25: 100% Original Epson | V25: IMAGENES DE PRODUCTOS/T504220-AL.jpg | W25: Tinta original Epson T504 Cian con sistema de llenado automático Ecofit (libre de derrames) para impresoras EcoTank L4150, L4160, L6161, L6171, L6191. | X25: Sistema Ecofit.
... A35: MTS-0032 | B35: Botella de Tinta Original Epson 544 Negra 65ml (T544120) | C35: Tintas y Suministros | D35: Epson | E35: T544120 | F35: Negro | G35: 010343941977 | H35: NUEVO | I35: 🟢 En Stock | J35: 1 | K35: 1 | L35: Estante Tintas - Nivel 4 | M35: 20000 | N35: 0.33331111 | O35: =IF(N35<1, ROUNDUP(M35/(1-N35), -3), M35) | P35: 0.16 | Q35: =IF((1-N35-P35)>0, ROUNDUP((M35+IF(O35>=90000,20000,0))/(1-N35-P35), -3), O35) | R35: =O35 | S35: =O35-M35 | T35: =IF(O35>0, (O35-M35)/O35, 0) | U35: 100% Original Epson | V35: IMAGENES DE PRODUCTOS/T544120.jpg | W35: Tinta original Epson 544 Negra de 65ml para impresoras EcoTank. | X35: Sistema Ecofit 544.
A36: MTS-0033 | B36: UPS Unipower UBI1000 Línea Interactiva 1000VA / 600W | C36: Energía y Respaldo / UPS | D36: Unipower | E36: UBI1000 | G36: 7707328610015 | H36: Nuevo | I36: 🟢 En Stock | J36: 3 | K36: 10 | L36: Estante A - Nivel 2 | M36: 152338 | N36: 0.31068466 | O36: =IF(N36<1, ROUNDUP(M36/(1-N36), -3), M36) | P36: 0.16 | Q36: =IF((1-N36-P36)>0, ROUNDUP((M36+IF(O36>=90000,20000,0))/(1-N36-P36), -3), O36) | R36: =O36 | S36: =O36-M36 | T36: =IF(O36>0, (O36-M36)/O36, 0) | U36: 36 Meses (3 Años) | V36: identidad visual max tech/Logo MAX Tech.png | W36: Es un sistema de respaldo con batería de 1000VA (600W). Si se corta la energía o hay un bajonazo de luz, mantiene encendido tu computador, módem de internet o punto de venta para que no pierdas tu trabajo y puedas apagar todo de forma segura. Trae 8 tomas protegidas y 3 años de garantía oficial. | X36: Producto de alta rotación para oficinas y hogares. | 3 unidades nuevas ingresadas (Factura FT-20168).
A37: MTS-0034 | B37: UPS Unipower UPI1500 Interactiva 1.5KVA / 900W con Pantalla | C37: Energía y Respaldo / UPS | D37: Unipower | E37: UPI1500 | G37: 7707328610022 | H37: Nuevo | I37: ⚪ Agotado | J37: 0 | K37: 2 | L37: Estante A - Nivel 1 | M37: 432546 | N37: 0.25035225 | O37: =IF(N37<1, ROUNDUP(M37/(1-N37), -3), M37) | P37: 0.16 | Q37: =IF((1-N37-P37)>0, ROUNDUP((M37+IF(O37>=90000,20000,0))/(1-N37-P37), -3), O37) | R37: =O37 | S37: =O37-M37 | T37: =IF(O37>0, (O37-M37)/O37, 0) | U37: 36 Meses (3 Años) | V37: identidad visual max tech/Logo MAX Tech.png | W37: UPS de alta potencia (1500VA / 900W) con pantalla digital frontal que te muestra el nivel de carga y batería. Puede respaldar 2 o 3 computadores al tiempo, o servidores y grabadores de cámaras de seguridad con mayor tiempo de batería. Cuenta con 3 años de garantía. | X37: Recomendada para empresas y salas de cómputo.
A38: MTS-0035 | B38: Regulador de Voltaje CDP R-AVR 3008 (3000VA / 1500W, 8 Salidas) | C38: Energía y Respaldo / Reguladores | D38: CDP | E38: R-AVR 3008 | G38: 0816869002280 | H38: Nuevo | I38: ⚪ Agotado | J38: 0 | K38: 1 | L38: Estante A - Nivel 2 | M38: 163096 | N38: 0.30001416 | O38: =IF(N38<1, ROUNDUP(M38/(1-N38), -3), M38) | P38: 0.16 | Q38: =IF((1-N38-P38)>0, ROUNDUP((M38+IF(O38>=90000,20000,0))/(1-N38-P38), -3), O38) | R38: =O38 | S38: =O38-M38 | T38: =IF(O38>0, (O38-M38)/O38, 0) | U38: 10 Años de Fábrica | V38: identidad visual max tech/Logo MAX Tech.png | W38: Regulador de alta potencia con 8 tomas y protección de hasta 3000VA. Protege tus equipos contra picos de voltaje y descargas eléctricas. Tiene temporizador especial de encendido para cuidar impresoras láser, fotocopiadoras o electrodomésticos. Viene con 10 años de garantía. | X38: 10 años de garantía directa de fábrica CDP.
A39: MTS-0036 | B39: Monitor Dahua 24" Panel IPS 144Hz 1ms Full HD | C39: Monitores y Pantallas | D39: Dahua | E39: DHI-LM24-A221Y | G39: 6938596001248 | H39: Nuevo | I39: ⚪ Agotado | J39: 0 | K39: 1 | L39: Estante B - Nivel 2 | M39: 265738 | N39: 0.25144014 | O39: =IF(N39<1, ROUNDUP(M39/(1-N39), -3), M39) | P39: 0.16 | Q39: =IF((1-N39-P39)>0, ROUNDUP((M39+IF(O39>=90000,20000,0))/(1-N39-P39), -3), O39) | R39: =O39 | S39: =O39-M39 | T39: =IF(O39>0, (O39-M39)/O39, 0) | U39: 36 Meses (3 Años) | V39: identidad visual max tech/Logo MAX Tech.png | W39: Pantalla de 24 pulgadas Full HD con tecnología IPS: los colores se ven vivos y claros desde cualquier ángulo. Al tener 144Hz de refresco y 1ms, todo el movimiento se ve supersuave, evitando el cansancio en los ojos tras varias horas de trabajo o juego. Incluye su cable HDMI y 3 años de garantía. | X39: Bisel ultradelgado y filtro de luz azul.
A40: MTS-0037 | B40: Monitor Dahua LED 27 Pulgadas FHD 144Hz 1ms IPS (DHI-LM27-A221Y) | C40: Monitores y Pantallas | D40: Dahua | E40: DHI-LM27-A221Y | F40: Negro | G40: 6938596001279 | H40: NUEVO | I40: 🟢 En Stock | J40: 3 | K40: 11 | L40: Bodega / Taller - Estante Monitores | M40: 316143 | N40: 0.18937484 | O40: =IF(N40<1, ROUNDUP(M40/(1-N40), -3), M40) | P40: 0.16 | Q40: =IF((1-N40-P40)>0, ROUNDUP((M40+IF(O40>=90000,20000,0))/(1-N40-P40), -3), O40) | R40: =O40 | S40: =O40-M40 | T40: =IF(O40>0, (O40-M40)/O40, 0) | U40: 36 Meses (3 Años) | V40: IMAGENES DE PRODUCTOS/Monitor dahua led 27 pulgadas ips 144 hz full hd.webp | W40: • Pantalla: 27 Pulgadas Full HD (1920 x 1080) antirreflejo • Panel: IPS con ángulos de visión amplios de 178° • Tasa de refresco: 144 Hz ultrarrápida • Tiempo de respuesta: 1 ms • Conectividad: Puertos HDMI y VGA • Diseño: Biseles ultradelgados con base plástica resistente • Garantía oficial de 3 años Dahua. | X40: 10 unidades físicas selladas. Seriales: BLR01916302500002 a BLR01916302500646. Factura FT-9364. | 3 unidades nuevas ingresadas (Factura FT-20171).
A41: MTS-0038 | B41: Monitor Dahua 27" Panel IPS 100Hz Full HD | C41: Monitores y Pantallas | D41: Dahua | E41: DHI-LM27-A201H | G41: 6938596001271 | H41: Nuevo | I41: ⚪ Agotado | J41: 0 | K41: 1 | L41: Estante B - Nivel 1 | M41: 310243 | N41: 0.25061896 | O41: =IF(N41<1, ROUNDUP(M41/(1-N41), -3), M41) | P41: 0.16 | Q41: =IF((1-N41-P41)>0, ROUNDUP((M41+IF(O41>=90000,20000,0))/(1-N41-P41), -3), O41) | R41: =O41 | S41: =O41-M41 | T41: =IF(O41>0, (O41-M41)/O41, 0) | U41: 36 Meses (3 Años) | V41: identidad visual max tech/Logo MAX Tech.png | W41: Monitor de 27 pulgadas ideal para oficina y estudio. Su tasa de 100Hz ofrece mucha mayor suavidad que una pantalla convencional (60Hz), permitiéndote trabajar con comodidad durante toda la jornada. Incluye cable HDMI y 3 años de garantía. | X41: Pantalla ejecutiva de 27 pulgadas.
A42: MTS-0039 | B42: Portátil Dell 15 Intel Core i7 13va Gen 16GB RAM 512GB SSD 15.6" FHD | C42: Portátiles y Equipos | D42: Dell | E42: P112F-3XHY0 | G42: 884116443128 | H42: Nuevo | I42: ⚪ Agotado | J42: 0 | K42: 1 | L42: Vitrina Principal | M42: 2065526 | N42: 0.18002111 | O42: =IF(N42<1, ROUNDUP(M42/(1-N42), -3), M42) | P42: 0.15 | Q42: =IF((1-N42-P42)>0, ROUNDUP((M42+IF(O42>=90000,20000,0))/(1-N42-P42), -3), O42) | R42: =O42 | S42: =O42-M42 | T42: =IF(O42>0, (O42-M42)/O42, 0) | U42: 12 Meses Onsite Dell | V42: identidad visual max tech/Logo MAX Tech.png | W42: Portátil rápido y confiable con procesador Intel Core i7 de 13va generación (10 núcleos), 16GB de memoria RAM y disco sólido ultrarrápido de 512GB. Enciende en pocos segundos y abre cualquier programa al instante. Pantalla de 15.6 pulgadas antirreflejo con teclado numérico y garantía oficial de Dell por 1 año. | X42: Garantía Onsite directa con Dell.
A43: MTS-0040 | B43: Portátil Dell 15 Intel Core i7 13va Gen 16GB RAM 512GB SSD (RWCGN) | C43: Portátiles y Equipos | D43: Dell | E43: P112F-RWCGN | G43: 884116443135 | H43: Nuevo | I43: ⚪ Agotado | J43: 0 | K43: 1 | L43: Vitrina Principal | M43: 2648576 | N43: 0.16024831 | O43: =IF(N43<1, ROUNDUP(M43/(1-N43), -3), M43) | P43: 0.15 | Q43: =IF((1-N43-P43)>0, ROUNDUP((M43+IF(O43>=90000,20000,0))/(1-N43-P43), -3), O43) | R43: =O43 | S43: =O43-M43 | T43: =IF(O43>0, (O43-M43)/O43, 0) | U43: 12 Meses Onsite Dell | V43: identidad visual max tech/Logo MAX Tech.png | W43: Computador portátil de alto rendimiento con procesador Intel Core i7, 16GB de memoria y disco sólido NVMe de 512GB. Diseñado para trabajo profesional, contabilidad, diseño y multitarea exigente. Cuenta con 1 año de garantía oficial de fábrica con soporte a domicilio de Dell. | X43: Soporte técnico directo de fábrica.
A44: MTS-0041 | B44: Portátil Lenovo IdeaPad Slim 3 Intel Core i7 24GB RAM 512GB SSD 15.6" FHD | C44: Portátiles y Equipos | D44: Lenovo | E44: 83K100BRLM | G44: 197532341209 | H44: Nuevo | I44: ⚪ Agotado | J44: 0 | K44: 2 | L44: Vitrina Principal | M44: 2430833 | N44: 0.18015723 | O44: =IF(N44<1, ROUNDUP(M44/(1-N44), -3), M44) | P44: 0.15 | Q44: =IF((1-N44-P44)>0, ROUNDUP((M44+IF(O44>=90000,20000,0))/(1-N44-P44), -3), O44) | R44: =O44 | S44: =O44-M44 | T44: =IF(O44>0, (O44-M44)/O44, 0) | U44: 12 Meses Lenovo | V44: identidad visual max tech/Logo MAX Tech.png | W44: Un portátil con una potencia impresionante: viene de fábrica con 24GB de memoria RAM (más del doble de lo normal) y procesador Intel Core i7 de alto desempeño. Es liviano, delgado, elegante en color gris y perfecto si necesitas trabajar con programas pesados, virtualización o ingeniería sin que se ponga lento jamás. | X44: 24GB de memoria RAM de fábrica.
A45: MTS-0042 | B45: Workstation Lenovo ThinkPad P16s Core Ultra 7 16GB SSD 1TB Nvidia RTX PRO 500 6GB W11Pro | C45: Estaciones de Trabajo / Laptops Pro | D45: Lenovo ThinkPad | E45: 21QW000ALM | G45: 198153441928 | H45: Nuevo | I45: ⚪ Agotado | J45: 0 | K45: 1 | L45: Caja Fuerte / Vitrina VIP | M45: 8967320 | N45: 0.15001698 | O45: =IF(N45<1, ROUNDUP(M45/(1-N45), -3), M45) | P45: 0.14 | Q45: =IF((1-N45-P45)>0, ROUNDUP((M45+IF(O45>=90000,20000,0))/(1-N45-P45), -3), O45) | R45: =O45 | S45: =O45-M45 | T45: =IF(O45>0, (O45-M45)/O45, 0) | U45: 36 Meses (3 Años Onsite Premier) | V45: identidad visual max tech/Logo MAX Tech.png | W45: Estación de trabajo portátil de gama profesional. Cuenta con el nuevo procesador Intel Core Ultra 7 con inteligencia artificial integrada, 1TB de disco sólido, tarjeta gráfica dedicada NVIDIA RTX PRO 500 de 6GB, pantalla de 16 pulgadas y certificación militar de resistencia. Es la máquina definitiva para arquitectura (AutoCAD/Revit), modelado 3D, edición 4K e ingeniería. | X45: Garantía Premier Onsite de 3 años.
A46: MTS-0043 | B46: Router TP-Link Archer C86 AC1900 Dual-Band Gigabit Wi-Fi | C46: Redes y Conectividad | D46: TP-Link | E46: Archer C86 | G46: 6935364072345 | H46: Nuevo | I46: ⚪ Agotado | J46: 0 | K46: 1 | L46: Estante C - Nivel 2 | M46: 142018 | N46: 0.32048479 | O46: =IF(N46<1, ROUNDUP(M46/(1-N46), -3), M46) | P46: 0.16 | Q46: =IF((1-N46-P46)>0, ROUNDUP((M46+IF(O46>=90000,20000,0))/(1-N46-P46), -3), O46) | R46: =O46 | S46: =O46-M46 | T46: =IF(O46>0, (O46-M46)/O46, 0) | U46: 48 Meses (4 Años TP-Link) | V46: identidad visual max tech/Logo MAX Tech.png | W46: Router de alta velocidad y gran cobertura para casas o locales de 2 a 3 pisos. Transmite en dos bandas (2.4GHz y 5GHz) hasta 1900 Mbps para que conectes muchos celulares, televisores y computadores al tiempo sin que se caiga la señal. Trae 4 puertos de red Gigabit y 4 años de garantía. | X46: 4 años de garantía directa TP-Link.
A47: MTS-0044 | B47: Adaptador USB Wi-Fi 6E TP-Link Archer TXE70UH Tribanda AXE5400 | C47: Redes y Conectividad | D47: TP-Link | E47: Archer TXE70UH | G47: 6935364010538 | H47: Nuevo | I47: ⚪ Agotado | J47: 0 | K47: 1 | L47: Vitrina Accesorios | M47: 226100 | N47: 0.29999783 | O47: =IF(N47<1, ROUNDUP(M47/(1-N47), -3), M47) | P47: 0.16 | Q47: =IF((1-N47-P47)>0, ROUNDUP((M47+IF(O47>=90000,20000,0))/(1-N47-P47), -3), O47) | R47: =O47 | S47: =O47-M47 | T47: =IF(O47>0, (O47-M47)/O47, 0) | U47: 48 Meses (4 Años) | V47: identidad visual max tech/Logo MAX Tech.png | W47: Es la antena Wi-Fi USB más rápida del mercado. Se conecta a cualquier computador o portátil por USB y le da acceso a la nueva banda Wi-Fi 6E (6 GHz), libre de interferencias y con velocidad de hasta 5400 Mbps. Trae base con cable de extensión para colocar las antenas donde haya mejor señal. | X47: Garantía de 4 años.
A48: MTS-0045 | B48: Adaptador TP-Link UE330 USB 3.0 a Gigabit Ethernet + Hub 3 Puertos USB | C48: Redes y Adaptadores | D48: TP-Link | E48: UE330 | G48: 6935364091728 | H48: NUEVO | I48: ⚪ Agotado | J48: 0 | K48: 0 | L48: Caja 1 - Adaptadores | M48: 87500 | N48: 0.23244941 | O48: =IF(N48<1, ROUNDUP(M48/(1-N48), -3), M48) | P48: 0.16 | Q48: =IF((1-N48-P48)>0, ROUNDUP((M48+IF(O48>=90000,20000,0))/(1-N48-P48), -3), O48) | R48: =O48 | S48: =O48-M48 | T48: =IF(O48>0, (O48-M48)/O48, 0) | U48: 12 Meses | V48: IMAGENES DE PRODUCTOS/Adaptador_TP-Link_UE330.png | W48: Adaptador 2 en 1: te da un puerto de red Gigabit por cable (para cuando el Wi-Fi falla o tu portátil no tiene entrada de red RJ45) y al mismo tiempo te añade 3 puertos USB 3.0 rápidos para conectar memorias, mouse o teclado.
A49: MTS-0046 | B49: Adaptador Nano USB Wi-Fi TP-Link TL-WN725N 150Mbps | C49: Redes y Adaptadores | D49: TP-Link | E49: TL-WN725N | G49: 6935364050718 | H49: NUEVO | I49: 🟢 En Stock | J49: 2 | K49: 2 | L49: Caja 1 - Adaptadores | M49: 30244 | N49: 0.3951079 | O49: =IF(N49<1, ROUNDUP(M49/(1-N49), -3), M49) | P49: 0.17 | Q49: =IF((1-N49-P49)>0, ROUNDUP((M49+IF(O49>=90000,20000,0))/(1-N49-P49), -3), O49) | R49: =O49 | S49: =O49-M49 | T49: =IF(O49>0, (O49-M49)/O49, 0) | U49: 36 Meses (3 Años) | V49: IMAGENES DE PRODUCTOS/TL-WN725N.webp | W49: Antena Wi-Fi miniatura de bolsillo. Se conecta a cualquier computador de escritorio o portátil que no tenga Wi-Fi o tenga la tarjeta dañada y le da conexión inmediata a internet sin estorbar. Cuenta con 3 años de garantía.
A50: MTS-0047 | B50: Cámara de Seguridad Dahua Bullet Wi-Fi 6 5MP (Sirena, Luz, Audio 2 Vías, IP67) | C50: Seguridad y Videovigilancia | D50: Dahua | E50: DH-F5D-PV-2.8MM | G50: 6938596005826 | H50: Nuevo | I50: ⚪ Agotado | J50: 0 | K50: 1 | L50: Estante C - Seguridad | M50: 154591 | N50: 0.32196632 | O50: =IF(N50<1, ROUNDUP(M50/(1-N50), -3), M50) | P50: 0.16 | Q50: =IF((1-N50-P50)>0, ROUNDUP((M50+IF(O50>=90000,20000,0))/(1-N50-P50), -3), O50) | R50: =O50 | S50: =O50-M50 | T50: =IF(O50>0, (O50-M50)/O50, 0) | U50: 12 Meses | V50: identidad visual max tech/Logo MAX Tech.png | W50: Cámara de vigilancia inteligente con video 5MP de alta claridad y conexión Wi-Fi 6. Puedes ver en vivo y escuchar desde tu celular desde cualquier lugar. Si detecta personas no autorizadas, activa una luz disuasoria roja/azul y una sirena. Es resistente al agua y lluvia (IP67) y graba en tarjeta MicroSD. | X50: Funciona con la app oficial DMSS.
A51: MTS-0048 | B51: Impresora Multifuncional Epson EcoTank L6490 Tanque de Tinta Wi-Fi Dúplex ADF | C51: Impresión y Multifuncionales | D51: Epson | E51: C11CJ88301 | G51: 010343958937 | H51: Nuevo | I51: ⚪ Agotado | J51: 0 | K51: 2 | L51: Bodega Principal | M51: 1393124 | N51: 0.20027279 | O51: =IF(N51<1, ROUNDUP(M51/(1-N51), -3), M51) | P51: 0.15 | Q51: =IF((1-N51-P51)>0, ROUNDUP((M51+IF(O51>=90000,20000,0))/(1-N51-P51), -3), O51) | R51: =O51 | S51: =O51-M51 | T51: =IF(O51>0, (O51-M51)/O51, 0) | U51: 12 Meses (2 Años con registro) | V51: identidad visual max tech/Logo MAX Tech.png | W51: Impresora de alto rendimiento a tanque de tinta continua (EcoTank). Imprime por ambas caras de forma automática, tiene alimentador de hojas automático para escanear muchas páginas solas, pantalla táctil a color y conexión Wi-Fi para imprimir desde el celular o computador. Cada recarga rinde miles de páginas a un costo mínimo. | X51: Tinta pigmentada resistente al agua.
A52: MTS-0049 | B52: Impresora Térmica Epson TM-T20III POS de Recibos 80mm/58mm USB + Serial | C52: Impresión POS y Facturación | D52: Epson | E52: C31CH51001 | G52: 010343951112 | H52: Nuevo | I52: ⚪ Agotado | J52: 0 | K52: 1 | L52: Bodega Principal | M52: 608875 | N52: 0.25015302 | O52: =IF(N52<1, ROUNDUP(M52/(1-N52), -3), M52) | P52: 0.16 | Q52: =IF((1-N52-P52)>0, ROUNDUP((M52+IF(O52>=90000,20000,0))/(1-N52-P52), -3), O52) | R52: =O52 | S52: =O52-M52 | T52: =IF(O52>0, (O52-M52)/O52, 0) | U52: 36 Meses (3 Años) | V52: identidad visual max tech/Logo MAX Tech.png | W52: Impresora térmica de recibos y facturas para puntos de venta, restaurantes, farmacias y comercios. No usa tinta (imprime por calor en papel térmico), imprime muy rápido y corta el papel de forma automática. Compatible con cualquier software contable o de facturación electrónica. | X52: 3 años de garantía Epson.
A53: MTS-0050 | B53: Memoria USB Kingston 128GB DataTraveler Exodia S USB 3.2 | C53: Almacenamiento y Memorias | D53: Kingston | E53: DTXS/128GB | G53: 740617329582 | H53: Nuevo | I53: ⚪ Agotado | J53: 0 | K53: 2 | L53: Vitrina Accesorios | M53: 29036 | N53: 0.40741648 | O53: =IF(N53<1, ROUNDUP(M53/(1-N53), -3), M53) | P53: 0.17 | Q53: =IF((1-N53-P53)>0, ROUNDUP((M53+IF(O53>=90000,20000,0))/(1-N53-P53), -3), O53) | R53: =O53 | S53: =O53-M53 | T53: =IF(O53>0, (O53-M53)/O53, 0) | U53: 36 Meses (3 Años) | V53: identidad visual max tech/Logo MAX Tech.png | W53: Memoria USB de 128GB reales con tecnología USB 3.2 de alta velocidad. Te permite guardar y transportar fotos, videos pesados, música y documentos con rapidez y seguridad. Diseño con tapa protectora y 3 años de garantía. | X53: 3 años de garantía Kingston.
A54: MTS-0051 | B54: Memoria Micro SD ADATA 128GB Alta Resistencia 4K Video V30 | C54: Almacenamiento y Memorias | D54: ADATA | E54: AUSDX128GUI3V30SHA2-RA1 | G54: 4711085934529 | H54: Nuevo | I54: ⚪ Agotado | J54: 0 | K54: 3 | L54: Vitrina Accesorios | M54: 57126 | N54: 0.38573533 | O54: =IF(N54<1, ROUNDUP(M54/(1-N54), -3), M54) | P54: 0.16 | Q54: =IF((1-N54-P54)>0, ROUNDUP((M54+IF(O54>=90000,20000,0))/(1-N54-P54), -3), O54) | R54: =O54 | S54: =O54-M54 | T54: =IF(O54>0, (O54-M54)/O54, 0) | U54: 60 Meses (5 Años) | V54: identidad visual max tech/Logo MAX Tech.png | W54: Tarjeta de memoria MicroSD de 128GB de grado profesional para grabación continua. Está especialmente diseñada para cámaras de seguridad y dashcams de carro, soportando escritura constante en video 4K sin dañarse ni recalentarse. Incluye 5 años de garantía oficial. | X54: 5 años de garantía ADATA.
A55: MTS-0052 | B55: Memoria Micro SD 128GB Clase 10 con Adaptador SD | C55: Almacenamiento y Memorias | D55: Kingston / SanDisk | E55: ST2-128-S1 | G55: 740617301281 | H55: Nuevo | I55: ⚪ Agotado | J55: 0 | K55: 3 | L55: Vitrina Accesorios | M55: 95422 | N55: 0.35086633 | O55: =IF(N55<1, ROUNDUP(M55/(1-N55), -3), M55) | P55: 0.16 | Q55: =IF((1-N55-P55)>0, ROUNDUP((M55+IF(O55>=90000,20000,0))/(1-N55-P55), -3), O55) | R55: =O55 | S55: =O55-M55 | T55: =IF(O55>0, (O55-M55)/O55, 0) | U55: 24 Meses (2 Años) | V55: identidad visual max tech/Logo MAX Tech.png | W55: Tarjeta MicroSD de 128GB Clase 10 para celulares, tablets, consolas de videojuegos o cámaras. Incluye adaptador para tamaño SD estándar. | X55: 2 años de garantía.
A56: MTS-0053 | B56: Cargador Original Lenovo 65W USB Tipo C Laptop | C56: Cargadores y Fuentes | D56: Lenovo | E56: 4X20M26268 | G56: 191999201948 | H56: Nuevo | I56: ⚪ Agotado | J56: 0 | K56: 1 | L56: Caja 1 - Cargadores | M56: 72202 | N56: 0.38288361 | O56: =IF(N56<1, ROUNDUP(M56/(1-N56), -3), M56) | P56: 0.16 | Q56: =IF((1-N56-P56)>0, ROUNDUP((M56+IF(O56>=90000,20000,0))/(1-N56-P56), -3), O56) | R56: =O56 | S56: =O56-M56 | T56: =IF(O56>0, (O56-M56)/O56, 0) | U56: 12 Meses Lenovo | V56: identidad visual max tech/Logo MAX Tech.png | W56: Cargador original Lenovo de 65W con punta tipo C. Cuenta con carga rápida inteligente y sirve tanto para portátiles Lenovo, Dell, HP, Asus o MacBook, como para celulares modernos con puerto USB-C. | X56: Cargador original genuino.
A57: MTS-0054 | B57: Licencia Microsoft 365 Familia (1 Año, 6 Usuarios, 1TB OneDrive c/u) | C57: Software y Licencias | D57: Microsoft | E57: EP2-32295 | G57: 889842861234 | H57: Nuevo | I57: ⚪ Agotado | J57: 0 | K57: 1 | L57: Bóveda Digital | M57: 253530 | N57: 0.22229823 | O57: =IF(N57<1, ROUNDUP(M57/(1-N57), -3), M57) | P57: 0.15 | Q57: =IF((1-N57-P57)>0, ROUNDUP((M57+IF(O57>=90000,20000,0))/(1-N57-P57), -3), O57) | R57: =O57 | S57: =O57-M57 | T57: =IF(O57>0, (O57-M57)/O57, 0) | U57: 12 Meses Soporte Microsoft | V57: identidad visual max tech/Logo MAX Tech.png | W57: Suscripción oficial por 1 año para hasta 6 personas de tu familia o equipo. Cada persona recibe Word, Excel, PowerPoint y Outlook actualizados para PC, Mac o celular, más 1.000 GB (1 Terabyte) de almacenamiento seguro en la nube OneDrive. | X57: Código de activación oficial 100% legal.
A58: MTS-0055 | B58: Impresora Multifuncional HP LaserJet MFP Láser Monocromática | C58: Impresión y Multifuncionales | D58: HP | E58: HP LaserJet MFP | G58: 192018349120 | H58: Nuevo | I58: ⚪ Agotado | J58: 0 | K58: 1 | L58: Bodega Principal | M58: 780250 | N58: 0.25047959 | O58: =IF(N58<1, ROUNDUP(M58/(1-N58), -3), M58) | P58: 0.16 | Q58: =IF((1-N58-P58)>0, ROUNDUP((M58+IF(O58>=90000,20000,0))/(1-N58-P58), -3), O58) | R58: =O58 | S58: =O58-M58 | T58: =IF(O58>0, (O58-M58)/O58, 0) | U58: 12 Meses HP | V58: identidad visual max tech/Logo MAX Tech.png | W58: Impresora láser multifuncional (imprime, copia y escanea) en blanco y negro. La impresión láser es ultranítida, el texto no se corre con el agua y el tóner nunca se seca aunque pases meses sin imprimir. Perfecta para oficinas, negocios y despachos que requieren documentos impecables. | X58: Tóner láser de alta duración.
A59: MTS-0056 | B59: Mouse Inalámbrico Logitech M170 Óptico Color Rojo | C59: Periféricos y Accesorios | D59: Logitech | E59: 910-004941 | G59: 097855122711 | H59: Nuevo | I59: ⚪ Agotado | J59: 0 | K59: 1 | L59: Vitrina Accesorios | M59: 39705 | N59: 0.40737921 | O59: =IF(N59<1, ROUNDUP(M59/(1-N59), -3), M59) | P59: 0.17 | Q59: =IF((1-N59-P59)>0, ROUNDUP((M59+IF(O59>=90000,20000,0))/(1-N59-P59), -3), O59) | R59: =O59 | S59: =O59-M59 | T59: =IF(O59>0, (O59-M59)/O59, 0) | U59: 12 Meses Logitech | V59: identidad visual max tech/Logo MAX Tech.png | W59: Mouse inalámbrico compacto y supercómodo en color rojo. Se conecta con un pequeño receptor USB y funciona hasta a 10 metros de distancia. Su pila dura hasta 12 meses continuos sin necesidad de cambiarla y es compatible con cualquier computador. | X59: 1 año de batería incluida.
A60: MTS-0057 | B60: Memoria RAM Samsung 8GB DDR4 2400MHz SODIMM para Portátil (PC4-2400T) | C60: Almacenamiento y Memorias | D60: Samsung | E60: M471A1K43CB1-CRC | F60: Verde | G60: Sin código | H60: REMANUFACTURADO | I60: ⚪ Agotado | J60: 0 | K60: 0 | L60: Taller | M60: 180000 | N60: 0.19999644 | O60: =IF(N60<1, ROUNDUP(M60/(1-N60), -3), M60) | P60: 0.16 | Q60: =IF((1-N60-P60)>0, ROUNDUP((M60+IF(O60>=90000,20000,0))/(1-N60-P60), -3), O60) | R60: =O60 | S60: =O60-M60 | T60: =IF(O60>0, (O60-M60)/O60, 0) | U60: Sin garantía | V60: IMAGENES DE PRODUCTOS/DDR4_8GB_2400MHZ.webp | W60: • Capacidad: 8 GB • Tipo: Memoria RAM DDR4 SODIMM para computadores portátiles / laptops • Frecuencia / Velocidad: 2400 MHz (PC4-2400T) • Formato: 260 pines SODIMM • Voltaje: 1.2V • Latencia: CL17 • Ideal para repotenciar y acelerar portátiles de diversas marcas (HP, Lenovo, Dell, Asus, Acer). | X60: 100% testeada con MemTest86 en taller.
A61: MTS-0058 | B61: Botella de Tinta Original Epson T504 Magenta | C61: Tintas y Suministros | D61: Epson | E61: T504320-AL | F61: Magenta | H61: NUEVO | I61: 🟢 En Stock | J61: 1 | K61: 1 | L61: Taller | M61: 20000 | N61: 0.33331111 | O61: =IF(N61<1, ROUNDUP(M61/(1-N61), -3), M61) | P61: 0.16 | Q61: =IF((1-N61-P61)>0, ROUNDUP((M61+IF(O61>=90000,20000,0))/(1-N61-P61), -3), O61) | R61: =O61 | S61: =O61-M61 | T61: =IF(O61>0, (O61-M61)/O61, 0) | U61: 0 | V61: IMAGENES DE PRODUCTOS/t504302.jpg
A62: MTS-0059 | B62: cale usb para impresora 1.5 Mtrs | C62: Tintas y Suministros | F62: gris | G62: 80182 | H62: NUEVO | I62: 🟢 En Stock | J62: 1 | K62: 1 | L62: Taller | M62: 8000 | N62: 0.33327777 | O62: =IF(N62<1, ROUNDUP(M62/(1-N62), -3), M62) | P62: 0.16 | Q62: =IF((1-N62-P62)>0, ROUNDUP((M62+IF(O62>=90000,20000,0))/(1-N62-P62), -3), O62) | R62: =O62 | S62: =O62-M62 | T62: =IF(O62>0, (O62-M62)/O62, 0) | U62: Garantía oficial | V62: IMAGENES DE PRODUCTOS/cable_usb_para_impresora_1.5_mtrs.webp
A63: MTS-0060 | B63: Hub USB 3.0 4 Puertos Follow Me | C63: Tintas y Suministros | D63: Follow me | H63: NUEVO | I63: 🟢 En Stock | J63: 1 | K63: 1 | L63: Taller | M63: 8000 | N63: 0.33327777 | O63: =IF(N63<1, ROUNDUP(M63/(1-N63), -3), M63) | P63: 0.16 | Q63: =IF((1-N63-P63)>0, ROUNDUP((M63+IF(O63>=90000,20000,0))/(1-N63-P63), -3), O63) | R63: =O63 | S63: =O63-M63 | T63: =IF(O63>0, (O63-M63)/O63, 0) | U63: Garantía oficial | V63: IMAGENES DE PRODUCTOS/Hub-USB-3-4-Puertos-FollowMe-3565-1.webp
A64: MTS-0061 | B64: Disco Estado Sólido SSD M.2 NVMe 1TB ADATA Legend 710 PCIe Gen3 x4 | C64: Almacenamiento y Memorias | D64: ADATA | E64: ALEG-710-1TCS | F64: Azul / Negro | G64: 4711085635398 | H64: NUEVO | I64: 🟢 En Stock | J64: 3 | K64: 3 | L64: Vitrina Accesorios / Taller | M64: 530000 | N64: 0.13114612 | O64: =IF(N64<1, ROUNDUP(M64/(1-N64), -3), M64) | P64: 0.16 | Q64: =IF((1-N64-P64)>0, ROUNDUP((M64+IF(O64>=90000,20000,0))/(1-N64-P64), -3), O64) | R64: =O64 | S64: =O64-M64 | T64: =IF(O64>0, (O64-M64)/O64, 0) | U64: 6 Meses | V64: IMAGENES DE PRODUCTOS/ADATA_LEGEND_710_1TB.jpg | W64: • Capacidad: 1 TB (1000 GB) • Formato: M.2 2280 • Interfaz: PCIe Gen3 x4 NVMe 1.4 • Velocidad de lectura secuencial: Hasta 2.400 MB/s • Velocidad de escritura secuencial: Hasta 1.800 MB/s • Disipador térmico de aluminio incluido (reduce temperatura hasta 15%) • Compatible con PCs de escritorio y portátiles con slot M.2 NVMe. | X64: | 1 unidad nueva ingresada (Serial: 4P2220399418, Factura FEVO 34572).
A65: MTS-0062 | B65: Teclado para Portátil Acer Aspire E1-470 E5-471P V3-472 3830T 4830 Negro Español | C65: Periféricos y Accesorios | D65: Acer / Compatible | E65: 00002272 | F65: Negro | G65: Sin código | H65: NUEVO | I65: 🟢 En Stock | J65: 1 | K65: 1 | L65: Taller - Repuestos | M65: 50000 | N65: 0.30554591 | O65: =IF(N65<1, ROUNDUP(M65/(1-N65), -3), M65) | P65: 0.16 | Q65: =IF((1-N65-P65)>0, ROUNDUP((M65+IF(O65>=90000,20000,0))/(1-N65-P65), -3), O65) | R65: =O65 | S65: =O65-M65 | T65: =IF(O65>0, (O65-M65)/O65, 0) | U65: 6 Meses | V65: identidad visual max tech/Logo MAX Tech.png | W65: • Idioma / Distribución: Español con letra Ñ • Color: Negro mate • Compatibilidad: Acer Aspire E1-470, E1-470G, E1-472, E5-471, E5-471P, V3-472, 3830, 3830T, 4830, 4830T • Tipo de repuesto: Teclado de reemplazo de alta respuesta táctil. | X65: Serial: 2F50031050103. Factura FEVO 33009.
A66: MTS-0063 | B66: Disco Estado Sólido SSD 2.5" SATA III 240GB ADATA Ultimate SU650 | C66: Almacenamiento y Memorias | D66: ADATA | E66: ASU650SS-240GT-R | F66: Negro | G66: 4713435793672 | H66: NUEVO | I66: 🟢 En Stock | J66: 1 | K66: 1 | L66: Vitrina Accesorios / Taller | M66: 169000 | N66: 0.2958304 | O66: =IF(N66<1, ROUNDUP(M66/(1-N66), -3), M66) | P66: 0.16 | Q66: =IF((1-N66-P66)>0, ROUNDUP((M66+IF(O66>=90000,20000,0))/(1-N66-P66), -3), O66) | R66: =O66 | S66: =O66-M66 | T66: =IF(O66>0, (O66-M66)/O66, 0) | U66: 36 Meses (3 Años ADATA) | V66: IMAGENES DE PRODUCTOS/adata 240 gb sata.jpg | W66: • Capacidad: 240 GB • Factor de forma: 2.5 pulgadas (7 mm de grosor) • Interfaz: SATA III 6Gb/s (retrocompatible con SATA II) • Velocidad de lectura secuencial: Hasta 520 MB/s • Velocidad de escritura secuencial: Hasta 450 MB/s • Tecnología: Memoria 3D NAND Flash con caché SLC y corrección de errores ECC • Compatibilidad: Ideal para actualizar computadores de escritorio o portátiles y multiplicar su velocidad. | X66: Producto nuevo remisionado. Referencia SU650.
A67: MTS-0064 | B67: Caja / Cofre Externo para Disco Duro 2.5" SATA a USB 3.0 Transparente POSUGEAR | C67: Almacenamiento y Memorias | D67: POSUGEAR | E67: B0C9TGQ8F5 | F67: Transparente | G67: Sin código | H67: NUEVO | I67: 🟢 En Stock | J67: 1 | K67: 1 | L67: Vitrina Accesorios / Taller | M67: 21700 | N67: 0.37998229 | O67: =IF(N67<1, ROUNDUP(M67/(1-N67), -3), M67) | P67: 0.16 | Q67: =IF((1-N67-P67)>0, ROUNDUP((M67+IF(O67>=90000,20000,0))/(1-N67-P67), -3), O67) | R67: =O67 | S67: =O67-M67 | T67: =IF(O67>0, (O67-M67)/O67, 0) | U67: 6 Meses | V67: IMAGENES DE PRODUCTOS/61YDB9nALmL._AC_SL1500_.jpg | W67: • Compatibilidad: Discos duros (HDD) y unidades de estado sólido (SSD) de 2.5" SATA I/II/III (7mm a 9.5mm, hasta 6 TB) • Conexión: Interfaz USB 3.0 con soporte UASP de alta velocidad (transferencias de hasta 5 Gbps) • Diseño: Carcasa transparente en policarbonato ultrarresistente (permite ver qué disco está instalado) • Instalación: 100% libre de herramientas (Tool-Free), apertura fácil mediante tapa deslizable • Plug & Play: Conexión directa sin drivers en Windows, macOS, Linux, Smart TV, PS4, PS5 y Xbox. | X67: Carcasa transparente para disco duro externo 2.5 SATA. Pedido Amazon 111-4517322-7785837.
A68: MTS-0065 | B68: Batería Seca Recargable para UPS 12V 7.5Ah Powest (FL1275GS) | C68: Energía y Respaldo / UPS | D68: Powest | E68: FL1275GS | F68: Negro | G68: Sin código | H68: NUEVO | I68: 🟢 En Stock | J68: 1 | K68: 2 | L68: Estante Baterías / Taller | M68: 45000 | N68: 0.30768166 | O68: =IF(N68<1, ROUNDUP(M68/(1-N68), -3), M68) | P68: 0.16 | Q68: =IF((1-N68-P68)>0, ROUNDUP((M68+IF(O68>=90000,20000,0))/(1-N68-P68), -3), O68) | R68: =O68 | S68: =O68-M68 | T68: =IF(O68>0, (O68-M68)/O68, 0) | U68: 12 Meses (1 Año Powest) | V68: IMAGENES DE PRODUCTOS/bateria ups powest 12v7ah.jpg | W68: • Voltaje nominal: 12V DC • Capacidad: 7.5 Ah / 20Hr • Tecnología: VRLA / AGM (Plomo-Ácido sellada libre de mantenimiento, a prueba de fugas) • Terminales: Tipo F1 / Faston 187 (estándar para fácil conexión) • Aplicaciones: Reemplazo ideal para UPS interactivas (APC, Unitec, CDP, Powest, Forza), sistemas de alarma, cercas eléctricas, iluminación y plantas solares. | X68: 2 unidades físicas nuevas en taller. Modelo FL1275GS.
A69: MTS-0066 | B69: Cámara de Seguridad IMOU Ranger 2 Pro 5MP 3K Wi-Fi 360° Smart Tracking | C69: Seguridad y Videovigilancia | D69: IMOU | E69: IPC-S2EN-5R1S-3.6MM | F69: Blanco | G69: 6971927236594 | H69: NUEVO | I69: 🟢 En Stock | J69: 1 | K69: 2 | L69: Vitrina Seguridad / Taller | M69: 102578 | N69: 0.265 | O69: =IF(N69<1, ROUNDUP(M69/(1-N69), -3), M69) | P69: 0.16 | Q69: =IF((1-N69-P69)>0, ROUNDUP((M69+IF(O69>=90000,20000,0))/(1-N69-P69), -3), O69) | R69: =O69 | S69: =O69-M69 | T69: =IF(O69>0, (O69-M69)/O69, 0) | U69: 12 Meses (1 Año IMOU) | V69: IMAGENES DE PRODUCTOS/camara imou 3K 5MP wifi indoor smart.jpeg | W69: • Resolución: 5 Megapíxeles 3K Ultra HD (2880 x 1620) para máxima nitidez de imagen • Cobertura 360°: Giro horizontal de 0~355° e inclinación de -5~80° con seguimiento inteligente de movimiento (Smart Tracking) • Visión nocturna avanzada: Infrarrojo claro de hasta 10 metros en oscuridad total • Inteligencia Artificial: Detección precisa de humanos y mascotas con alertas instantáneas a la app IMOU Life • Audio bidireccional: Micrófono y altavoz integrados para hablar y escuchar en tiempo real • Alarma disuasoria: Sirena integrada para ahuyentar intrusos y detección de sonidos anormales • Almacenamiento: Ranura para tarjeta Micro SD de hasta 512 GB y opción de almacenamiento en la nube • Conectividad: Wi-Fi 2.4 GHz y alimentación moderna por puerto USB Tipo-C. | X69: 2 unidades nuevas selladas en taller. Factura FT-18220.
A70: MTS-0067 | B70: Memoria Micro SD SanDisk Ultra 128GB microSDXC UHS-I Clase 10 (100MB/s) | C70: Almacenamiento y Memorias | D70: SanDisk | E70: SDSQUNR-128G-GN6MN | F70: Rojo / Gris | G70: 619659181740 | H70: NUEVO | I70: 🟢 En Stock | J70: 1 | K70: 3 | L70: Vitrina Accesorios / Taller | M70: 90594 | N70: 0.21221924 | O70: =IF(N70<1, ROUNDUP(M70/(1-N70), -3), M70) | P70: 0.16 | Q70: =IF((1-N70-P70)>0, ROUNDUP((M70+IF(O70>=90000,20000,0))/(1-N70-P70), -3), O70) | R70: =O70 | S70: =O70-M70 | T70: =IF(O70>0, (O70-M70)/O70, 0) | U70: 12 Meses (1 Año SanDisk) | V70: IMAGENES DE PRODUCTOS/micro sd 128gb c10 sandisk.jpeg | W70: • Capacidad: 128 GB de almacenamiento de alta velocidad • Velocidad de transferencia: Hasta 100 MB/s de lectura rápida para transferir fotos y videos en segundos • Rendimiento: Clase 10, UHS Speed Class 1 (U1) y A1 (optimizada para apps y cámaras) • Grabación de video: Optimizada para video Full HD (1080p) continuo y fotografía de alta resolución • Resistencia extrema: Diseñada a prueba de agua, golpes, rayos X y temperaturas extremas • Compatibilidad: Smartphones, tablets, cámaras de seguridad (IMOU, Tapo, Dahua), drones y Nintendo Switch. | X70: 3 unidades nuevas selladas. Pedido Amazon 111-3727652-1457013.
A71: MTS-0068 | B71: Diadema con Micrófono USB Genius HS-230U para Oficina y Teletrabajo | C71: Periféricos y Accesorios | D71: Genius | E71: HS-230U / 31710021401 | F71: Negro | G71: 4710268257257 | H71: NUEVO | I71: 🟢 En Stock | J71: 1 | K71: 1 | L71: Vitrina Periféricos / Taller | M71: 38675 | N71: 0.14 | O71: =IF(N71<1, ROUNDUP(M71/(1-N71), -3), M71) | P71: 0.16 | Q71: =IF((1-N71-P71)>0, ROUNDUP((M71+IF(O71>=90000,20000,0))/(1-N71-P71), -3), O71) | R71: =O71 | S71: =O71-M71 | T71: =IF(O71>0, (O71-M71)/O71, 0) | U71: 12 Meses (1 Año Genius) | V71: IMAGENES DE PRODUCTOS/Diadema usb HS-230U Genius.jpeg | W71: • Conexión: USB Plug & Play inmediata (sin necesidad de controladores ni adaptadores) • Micrófono: Micrófono omnidireccional con cancelación de ruido y brazo ajustable y flexible • Comodidad: Diadema ultraliviana ajustable con almohadillas acolchadas suaves para largas jornadas • Control en cable: Control integrado de volumen y botón de silenciado rápido (Mute) • Sonido: Drivers de 30 mm para llamadas nítidas y reproducción clara de audio • Compatibilidad: Windows, macOS, Zoom, Microsoft Teams, Google Meet, Skype y teletrabajo. | X71: 1 unidad nueva sellada. Factura FT-18220.
A72: MTS-0069 | B72: Cámara Domo Dahua 2MP Full-Color 1080p Lente 3.6mm Audio Integrado IP67 | C72: Seguridad y Videovigilancia | D72: Dahua | E72: DH-HAC-HDW1239TN-A-LED-3.6MM | F72: Blanco | G72: 6938596001286 | H72: NUEVO | I72: 🟢 En Stock | J72: 2 | K72: 2 | L72: Vitrina Seguridad / Taller | M72: 108528 | N72: 0.2 | O72: =IF(N72<1, ROUNDUP(M72/(1-N72), -3), M72) | P72: 0.16 | Q72: =IF((1-N72-P72)>0, ROUNDUP((M72+IF(O72>=90000,20000,0))/(1-N72-P72), -3), O72) | R72: =O72 | S72: =O72-M72 | T72: =IF(O72>0, (O72-M72)/O72, 0) | U72: 24 Meses (2 Años Dahua) | V72: IMAGENES DE PRODUCTOS/camara ajhua HDCVI 2MP 3.6mm.jpeg | W72: • Tecnología Full-Color 24/7: Imágenes y videos a color las 24 horas del día incluso en oscuridad total • Resolución: 2 Megapíxeles 1080p Full HD (1920 x 1080) a 30 fps • Lente: Fijo de 3.6 mm con apertura focal F1.6 de alta captación de luz • Iluminación LED blanca cálida: Alcance de hasta 20 metros para visión nocturna nítida a color • Audio incorporado: Micrófono integrado de alta sensibilidad transmitido por el mismo cable coaxial • Formato 4 en 1 conmutable: Compatible con formatos de video CVI, TVI, AHD y CVBS • Protección para intemperie: Grado de protección IP67 resistente al agua, lluvia y polvo. | X72: 2 unidades nuevas selladas. Factura FT-18220.
A73: MTS-0070 | B73: Cable Adaptador USB 2.0 a Puerto Serial RS232 DB9 Macho Jaltech | C73: Periféricos y Accesorios | D73: Jaltech | E73: 01132 / USB-RS232-DB9 | F73: Azul / Negro | G73: Sin código | H73: NUEVO | I73: 🟢 En Stock | J73: 1 | K73: 1 | L73: Vitrina Accesorios / Taller | M73: 14000 | N73: 0.3 | O73: =IF(N73<1, ROUNDUP(M73/(1-N73), -3), M73) | P73: 0.16 | Q73: =IF((1-N73-P73)>0, ROUNDUP((M73+IF(O73>=90000,20000,0))/(1-N73-P73), -3), O73) | R73: =O73 | S73: =O73-M73 | T73: =IF(O73>0, (O73-M73)/O73, 0) | U73: 6 Meses | V73: IMAGENES DE PRODUCTOS/Cable usb a puerto serial RS232.jpeg | W73: • Conector: USB 2.0 Macho a Conector Serial DB9 (RS232) Macho • Chipset: Controlador de alta compatibilidad para comunicación serial estable y sin pérdidas • Tasa de transferencia: Soporta velocidades de datos de hasta 1 Mbps • Aplicaciones: Conexión de impresoras POS/fiscales, balanzas, switches, routers Cisco, PLCs y GPS • Compatibilidad: Funciona en Windows 11, 10, 8.1, 7, Linux y macOS. | X73: 1 unidad nueva. Cable adaptador USB a serial RS232.
A74: MTS-0071 | B74: Ventilador Cooler Fan 40x40x10mm 12V 0.1A para DVR, Mini PC e Impresoras 3D | C74: Componentes y Repuestos | D74: Genérico / OEM | E74: FAN-4010-12V | F74: Negro | G74: Sin código | H74: NUEVO | I74: 🟢 En Stock | J74: 1 | K74: 1 | L74: Taller - Repuestos | M74: 11000 | N74: 0.22 | O74: =IF(N74<1, ROUNDUP(M74/(1-N74), -3), M74) | P74: 0.16 | Q74: =IF((1-N74-P74)>0, ROUNDUP((M74+IF(O74>=90000,20000,0))/(1-N74-P74), -3), O74) | R74: =O74 | S74: =O74-M74 | T74: =IF(O74>0, (O74-M74)/O74, 0) | U74: 3 Meses | V74: IMAGENES DE PRODUCTOS/Ventilador para dvr .jpeg | W74: • Dimensiones: 40 mm x 40 mm x 10 mm (1.5 pulgadas aprox.) • Alimentación: 12V DC a 0.1 Amperios (bajo consumo y operación silenciosa) • Conector: Terminal estándar de 2 pines (rojo positivo / negro negativo) • Aplicaciones: Extractor de calor y disipador de reemplazo para grabadores DVR/NVR (Dahua, Hikvision), mini PCs, impresoras 3D, routers y fuentes de poder. | X74: 1 unidad nueva. Ventilador micro cooler 4010 12V 0.1A.
A75: MTS-0072 | B75: Memoria RAM Samsung 4GB DDR4 2400MHz SODIMM para Portátil (PC4-2400T) | C75: Memorias | D75: Samsung | H75: REMANUFACTURADO | I75: 🟢 En Stock | J75: 2 | K75: 2 | L75: Taller | M75: 50000 | N75: 0.5 | O75: =IF(N75<1, ROUNDUP(M75/(1-N75), -3), M75) | P75: 0.16 | Q75: =IF((1-N75-P75)>0, ROUNDUP((M75+IF(O75>=90000,20000,0))/(1-N75-P75), -3), O75) | R75: =O75 | S75: =O75-M75 | T75: =IF(O75>0, (O75-M75)/O75, 0) | U75: Garantía oficial | V75: identidad visual max tech/Logo MAX Tech.png
A76: JAL838L | B76: IMPRESORA TÉRMICA 2 EN 1 RECIBOS Y ETIQUETAS | C76: Tintas y Suministros | D76: Jaltech | F76: Negra | H76: NUEVO | I76: ⚪ Agotado | J76: 0 | K76: 0 | L76: Taller | M76: 370000 | N76: 0.105 | O76: =IF(N76<1, ROUNDUP(M76/(1-N76), -3), M76) | P76: 0.16 | Q76: =IF((1-N76-P76)>0, ROUNDUP((M76+IF(O76>=90000,20000,0))/(1-N76-P76), -3), O76) | R76: =O76 | S76: =O76-M76 | T76: =IF(O76>0, (O76-M76)/O76, 0) | U76: Garantía oficial | V76: IMAGENES DE PRODUCTOS/impresora_pos_doblre_proposito_jaltech.jpeg | W76: IMPRESORA TÉRMICA 2 EN 1 RECIBOS Y ETIQUETAS · Impresora de doble función · Modo de impresión de etiquetas · Modo de impresión de recibos · Alta velocidad · Puerto RJ45 · Puerto USB · Amplia compatibilidad · Windows, Linux, Lac, Android · Impresora doble propósito: · Modo de impresión de etiquetas (cód. De barras) · Modo de impresión de recibos (facturación) · Tipo de impresión: térmica directa · Comando de impresión: TSPL (compatible con CPCL/ESC/POS) · Incluye software para elaboración de etiquetas · Tipo de papel: rollo spapel térmico y papel termoadhesivo · Ancho de papel: de 20mm a 82mm · Grosor de papel: de 0,06 a 0,19 mm · Diámetro de papel: 82mm · Ancho de impresión: 76mm · Tipos de rollo de papel: papel continuo, papel de etiquetas · Velocidad de impresión: 220mm/s en modo facturación, · 127mm/s en modo cód. De barras · Puertos: USB, RJ45 Lan y RJ11 para cajón monedero · Memoria: RAM 4mb, flash 4mb · Resolución: 203 ppp · Corte de papel: manual · Vida útil del cabezal de impresión: unos 100Km · Botón de encendido y apagado · Adaptador de energía: 24v/2,5a 3pin · Compatibilidad: Windows y Android en modo cód. De barras, · Win, linux, Android y mac en modo facturación · SDK: iOS/Android/Windows · Sensores en modo cód. De barras: sensor de temperatura del cabezal/ fin del papel/cubierta abierta/sensor gap (espacios) · Sensores en modo facturación: sensor de temperatura del cabezal/fin del papel/cubierta abierta · Temperatura de trabajo: 5 - 45 °c humedad: rh 10-80% · Dimensiones: 212x140x144mm · Peso: 0,94 Kg · Contenido de la caja: impresora, adaptador de papel, adaptador de corriente, cable de poder, cable USB, CD, manual. · Compatibilidad de codificación: 1d: código 128 / ean1281 itf/ código 39/ código 39c / código39s / código931 ean13 / ean13+21/ean13+5/ean8 / ean8+21 ean8+5 / codabar / upc-a /upca+2 /upca+5/upce /upce+21 upce+51 MSI / msic / plessey / itf14 / ean14. · 2d: pdf417/ código qr/ datamatrix. Volver
A77: MTS-0073 | B77: Cámara de Seguridad IMOU Ranger 2 Dual 10MP (5MP+5MP) Wi-Fi 6 360° Smart Full-Color | C77: Seguridad y Videovigilancia | D77: IMOU | E77: IPC-S20EN-10M0S-3.6MM | F77: Blanco | G77: Sin código | H77: NUEVO | I77: 🟢 En Stock | J77: 2 | K77: 2 | L77: Vitrina Seguridad / Taller | M77: 187400 | N77: 0.30074366 | O77: =IF(N77<1, ROUNDUP(M77/(1-N77), -3), M77) | P77: 0.16 | Q77: =IF((1-N77-P77)>0, ROUNDUP((M77+IF(O77>=90000,20000,0))/(1-N77-P77), -3), O77) | R77: =O77 | S77: =O77-M77 | T77: =IF(O77>0, (O77-M77)/O77, 0) | U77: 12 Meses (1 Año Oficial IMOU) | V77: identidad visual max tech/Logo MAX Tech.png | W77: • Doble lente de 10MP en total: Lente fijo 5MP 3K + Lente robótico PT 5MP 3K con giro 360° e inclinación • Cobertura simultánea: Monitorea dos áreas al mismo tiempo con una sola cámara • Visión nocturna Smart Full-Color: 4 modos inteligentes de visión nocturna a todo color • Conectividad Wi-Fi 6 (2.4 GHz y 5 GHz) de alta velocidad y máxima estabilidad de señal • Detección inteligente por IA: Reconoce humanos y mascotas con seguimiento automático de movimiento • Audio bidireccional y botón de llamada directa (One-touch call) desde la cámara al celular • Sirena y alarma disuasoria con detección de sonidos anormales • Puerto de alimentación USB-C y ranura para tarjeta Micro SD de hasta 512 GB. | X77: 2 unidades nuevas selladas en taller. Factura FT-20168.
A78: MTS-0074 | B78: Router TP-Link Archer BE550 Tribanda Wi-Fi 7 BE9300 9.3Gbps Puertos 2.5G | C78: Redes y Conectividad | D78: TP-Link | E78: Archer BE550 | F78: Negro | G78: Sin código | H78: NUEVO | I78: 🟢 En Stock | J78: 1 | K78: 1 | L78: Estante Redes / Taller | M78: 798490 | N78: 0.20070991 | O78: =IF(N78<1, ROUNDUP(M78/(1-N78), -3), M78) | P78: 0.16 | Q78: =IF((1-N78-P78)>0, ROUNDUP((M78+IF(O78>=90000,20000,0))/(1-N78-P78), -3), O78) | R78: =O78 | S78: =O78-M78 | T78: =IF(O78>0, (O78-M78)/O78, 0) | U78: 24 Meses (2 Años Oficial TP-Link) | V78: identidad visual max tech/Logo MAX Tech.png | W78: • Tecnología Wi-Fi 7 de última generación con velocidad tribanda extrema de hasta 9.300 Mbps (9.3 Gbps) • Operación Multi-Link (MLO) y canales de 320 MHz para latencia ultrabaja y máxima estabilidad • 5 puertos Ethernet 2.5 Gbps (1 puerto WAN 2.5G + 4 puertos LAN 2.5G) ideales para fibra óptica ultrarrápida • 6 antenas internas óptimamente posicionadas con tecnología Beamforming para cobertura omnidireccional • Puerto USB 3.0 de alta velocidad para compartir archivos y crear almacenamiento NAS local • Procesador de alta potencia para streaming 8K/4K simultáneo, gaming profesional y realidad virtual (VR) • Seguridad avanzada TP-Link HomeShield y compatibilidad con EasyMesh. | X78: 1 unidad nueva sellada. Factura FT-20172.
A79: MTS-0075 | B79: Disco Estado Sólido SSD 2.5" SATA III 1TB (1000GB) ADATA Ultimate SU650 | C79: Almacenamiento y Memorias | D79: ADATA | E79: ASU650SS-1TT-R / SU650 1TB | F79: Negro | G79: Sin código | H79: NUEVO | I79: 🟢 En Stock | J79: 1 | K79: 1 | L79: Vitrina Accesorios / Taller | M79: 515000 | N79: 0.20154915 | O79: =IF(N79<1, ROUNDUP(M79/(1-N79), -3), M79) | P79: 0.16 | Q79: =IF((1-N79-P79)>0, ROUNDUP((M79+IF(O79>=90000,20000,0))/(1-N79-P79), -3), O79) | R79: =O79 | S79: =O79-M79 | T79: =IF(O79>0, (O79-M79)/O79, 0) | U79: 36 Meses (3 Años Oficial ADATA) | V79: identidad visual max tech/Logo MAX Tech.png | W79: • Capacidad: 1 TB (1.000 GB) de almacenamiento sólido • Factor de forma: 2.5 pulgadas (7 mm de grosor, ultrafino) • Interfaz: SATA III 6Gb/s (retrocompatible con SATA II) • Velocidad de lectura secuencial: Hasta 520 MB/s • Velocidad de escritura secuencial: Hasta 450 MB/s • Tecnología: Memoria 3D NAND Flash con caché SLC y corrección de errores ECC • Ideal para repotenciar portátiles y computadores de escritorio con máxima capacidad y velocidad. | X79: 1 unidad nueva sellada. Serial: 4P3621895537. Factura FEVO 34572.
A80: MTS-0076 | B80: Caja / Cofre Externo para Disco SSD M.2 NVMe a USB 3.0 / USB-C Negro | C80: Almacenamiento y Memorias | D80: Digital MTX / OEM | E80: 00003583 / CASE-M2-NVME-USB | F80: Negro | G80: Sin código | H80: NUEVO | I80: 🟢 En Stock | J80: 1 | K80: 1 | L80: Vitrina Accesorios / Taller | M80: 45000 | N80: 0.33822556 | O80: =IF(N80<1, ROUNDUP(M80/(1-N80), -3), M80) | P80: 0.16 | Q80: =IF((1-N80-P80)>0, ROUNDUP((M80+IF(O80>=90000,20000,0))/(1-N80-P80), -3), O80) | R80: =O80 | S80: =O80-M80 | T80: =IF(O80>0, (O80-M80)/O80, 0) | U80: 3 Meses | V80: identidad visual max tech/Logo MAX Tech.png | W80: • Compatibilidad: Discos sólidos SSD M.2 NVMe PCIe M-Key y B+M Key (tamaños 2230, 2242, 2260, 2280) • Conexión: Interfaz USB 3.0 / USB-C de alta velocidad (transferencias de hasta 10 Gbps) • Carcasa: Construcción metálica en aluminio negro para disipación térmica óptima • Instalación fácil y rápida sin herramientas complicadas • Plug & Play: Compatible con Windows, macOS, Linux, Smart TV y consolas de videojuegos. | X80: 1 unidad nueva. Factura FEVO 34572.

Sheet 📊 Resumen y Métricas
A1: PANEL DE CONTROL — VALORIZACIÓN Y ROTACIÓN DE INVENTARIO
B3: VALOR TOTAL EN STOCK (COSTO) | D3: VALOR TOTAL EN STOCK (VENTA) | F3: UTILIDAD NETA ESTIMADA EN STOCK
B4: ='📦 Inventario Maestro'!M60 | D4: ='📦 Inventario Maestro'!O60 | F4: ='📦 Inventario Maestro'!S60
A7: DESGLOSE DE MERCANCÍA POR CATEGORÍA
A8: Categoría | B8: Referencias | C8: Stock Actual | D8: Histórico Comprado | E8: Valor Costo Stock | F8: Valor Venta Stock | G8: Utilidad en Stock
A9: Accesorios y Fundas | B9: =COUNTIF('📦 Inventario Maestro'!$C$4:$C$59, A9) | C9: =SUMIF('📦 Inventario Maestro'!$C$4:$C$59, A9, '📦 Inventario Maestro'!$J$4:$J$59) | D9: =SUMIF('📦 Inventario Maestro'!$C$4:$C$59, A9, '📦 Inventario Maestro'!$K$4:$K$59) | E9: =SUMPRODUCT(('📦 Inventario Maestro'!$C$4:$C$59=A9)*('📦 Inventario Maestro'!$M$4:$M$59)*('📦 Inventario Maestro'!$J$4:$J$59)) | F9: =SUMPRODUCT(('📦 Inventario Maestro'!$C$4:$C$59=A9)*('📦 Inventario Maestro'!$O$4:$O$59)*('📦 Inventario Maestro'!$J$4:$J$59)) | G9: =F9-E9
A10: Almacenamiento y Memorias | B10: =COUNTIF('📦 Inventario Maestro'!$C$4:$C$59, A10) | C10: =SUMIF('📦 Inventario Maestro'!$C$4:$C$59, A10, '📦 Inventario Maestro'!$J$4:$J$59) | D10: =SUMIF('📦 Inventario Maestro'!$C$4:$C$59, A10, '📦 Inventario Maestro'!$K$4:$K$59) | E10: =SUMPRODUCT(('📦 Inventario Maestro'!$C$4:$C$59=A10)*('📦 Inventario Maestro'!$M$4:$M$59)*('📦 Inventario Maestro'!$J$4:$J$59)) | F10: =SUMPRODUCT(('📦 Inventario Maestro'!$C$4:$C$59=A10)*('📦 Inventario Maestro'!$O$4:$O$59)*('📦 Inventario Maestro'!$J$4:$J$59)) | G10: =F10-E10
A11: Cargadores y Fuentes | B11: =COUNTIF('📦 Inventario Maestro'!$C$4:$C$59, A11) | C11: =SUMIF('📦 Inventario Maestro'!$C$4:$C$59, A11, '📦 Inventario Maestro'!$J$4:$J$59) | D11: =SUMIF('📦 Inventario Maestro'!$C$4:$C$59, A11, '📦 Inventario Maestro'!$K$4:$K$59) | E11: =SUMPRODUCT(('📦 Inventario Maestro'!$C$4:$C$59=A11)*('📦 Inventario Maestro'!$M$4:$M$59)*('📦 Inventario Maestro'!$J$4:$J$59)) | F11: =SUMPRODUCT(('📦 Inventario Maestro'!$C$4:$C$59=A11)*('📦 Inventario Maestro'!$O$4:$O$59)*('📦 Inventario Maestro'!$J$4:$J$59)) | G11: =F11-E11
A12: Energía Solar y Electrónica | B12: =COUNTIF('📦 Inventario Maestro'!$C$4:$C$59, A12) | C12: =SUMIF('📦 Inventario Maestro'!$C$4:$C$59, A12, '📦 Inventario Maestro'!$J$4:$J$59) | D12: =SUMIF('📦 Inventario Maestro'!$C$4:$C$59, A12, '📦 Inventario Maestro'!$K$4:$K$59) | E12: =SUMPRODUCT(('📦 Inventario Maestro'!$C$4:$C$59=A12)*('📦 Inventario Maestro'!$M$4:$M$59)*('📦 Inventario Maestro'!$J$4:$J$59)) | F12: =SUMPRODUCT(('📦 Inventario Maestro'!$C$4:$C$59=A12)*('📦 Inventario Maestro'!$O$4:$O$59)*('📦 Inventario Maestro'!$J$4:$J$59)) | G12: =F12-E12
A13: Energía y Respaldo / Reguladores | B13: =COUNTIF('📦 Inventario Maestro'!$C$4:$C$59, A13) | C13: =SUMIF('📦 Inventario Maestro'!$C$4:$C$59, A13, '📦 Inventario Maestro'!$J$4:$J$59) | D13: =SUMIF('📦 Inventario Maestro'!$C$4:$C$59, A13, '📦 Inventario Maestro'!$K$4:$K$59) | E13: =SUMPRODUCT(('📦 Inventario Maestro'!$C$4:$C$59=A13)*('📦 Inventario Maestro'!$M$4:$M$59)*('📦 Inventario Maestro'!$J$4:$J$59)) | F13: =SUMPRODUCT(('📦 Inventario Maestro'!$C$4:$C$59=A13)*('📦 Inventario Maestro'!$O$4:$O$59)*('📦 Inventario Maestro'!$J$4:$J$59)) | G13: =F13-E13
A14: Energía y Respaldo / UPS | B14: =COUNTIF('📦 Inventario Maestro'!$C$4:$C$59, A14) | C14: =SUMIF('📦 Inventario Maestro'!$C$4:$C$59, A14, '📦 Inventario Maestro'!$J$4:$J$59) | D14: =SUMIF('📦 Inventario Maestro'!$C$4:$C$59, A14, '📦 Inventario Maestro'!$K$4:$K$59) | E14: =SUMPRODUCT(('📦 Inventario Maestro'!$C$4:$C$59=A14)*('📦 Inventario Maestro'!$M$4:$M$59)*('📦 Inventario Maestro'!$J$4:$J$59)) | F14: =SUMPRODUCT(('📦 Inventario Maestro'!$C$4:$C$59=A14)*('📦 Inventario Maestro'!$O$4:$O$59)*('📦 Inventario Maestro'!$J$4:$J$59)) | G14: =F14-E14
A15: Estaciones de Trabajo / Laptops Pro | B15: =COUNTIF('📦 Inventario Maestro'!$C$4:$C$59, A15) | C15: =SUMIF('📦 Inventario Maestro'!$C$4:$C$59, A15, '📦 Inventario Maestro'!$J$4:$J$59) | D15: =SUMIF('📦 Inventario Maestro'!$C$4:$C$59, A15, '📦 Inventario Maestro'!$K$4:$K$59) | E15: =SUMPRODUCT(('📦 Inventario Maestro'!$C$4:$C$59=A15)*('📦 Inventario Maestro'!$M$4:$M$59)*('📦 Inventario Maestro'!$J$4:$J$59)) | F15: =SUMPRODUCT(('📦 Inventario Maestro'!$C$4:$C$59=A15)*('📦 Inventario Maestro'!$O$4:$O$59)*('📦 Inventario Maestro'!$J$4:$J$59)) | G15: =F15-E15
A16: Impresión POS y Facturación | B16: =COUNTIF('📦 Inventario Maestro'!$C$4:$C$59, A16) | C16: =SUMIF('📦 Inventario Maestro'!$C$4:$C$59, A16, '📦 Inventario Maestro'!$J$4:$J$59) | D16: =SUMIF('📦 Inventario Maestro'!$C$4:$C$59, A16, '📦 Inventario Maestro'!$K$4:$K$59) | E16: =SUMPRODUCT(('📦 Inventario Maestro'!$C$4:$C$59=A16)*('📦 Inventario Maestro'!$M$4:$M$59)*('📦 Inventario Maestro'!$J$4:$J$59)) | F16: =SUMPRODUCT(('📦 Inventario Maestro'!$C$4:$C$59=A16)*('📦 Inventario Maestro'!$O$4:$O$59)*('📦 Inventario Maestro'!$J$4:$J$59)) | G16: =F16-E16
A17: Impresión y Multifuncionales | B17: =COUNTIF('📦 Inventario Maestro'!$C$4:$C$59, A17) | C17: =SUMIF('📦 Inventario Maestro'!$C$4:$C$59, A17, '📦 Inventario Maestro'!$J$4:$J$59) | D17: =SUMIF('📦 Inventario Maestro'!$C$4:$C$59, A17, '📦 Inventario Maestro'!$K$4:$K$59) | E17: =SUMPRODUCT(('📦 Inventario Maestro'!$C$4:$C$59=A17)*('📦 Inventario Maestro'!$M$4:$M$59)*('📦 Inventario Maestro'!$J$4:$J$59)) | F17: =SUMPRODUCT(('📦 Inventario Maestro'!$C$4:$C$59=A17)*('📦 Inventario Maestro'!$O$4:$O$59)*('📦 Inventario Maestro'!$J$4:$J$59)) | G17: =F17-E17
A18: Monitores y Pantallas | B18: =COUNTIF('📦 Inventario Maestro'!$C$4:$C$59, A18) | C18: =SUMIF('📦 Inventario Maestro'!$C$4:$C$59, A18, '📦 Inventario Maestro'!$J$4:$J$59) | D18: =SUMIF('📦 Inventario Maestro'!$C$4:$C$59, A18, '📦 Inventario Maestro'!$K$4:$K$59) | E18: =SUMPRODUCT(('📦 Inventario Maestro'!$C$4:$C$59=A18)*('📦 Inventario Maestro'!$M$4:$M$59)*('📦 Inventario Maestro'!$J$4:$J$59)) | F18: =SUMPRODUCT(('📦 Inventario Maestro'!$C$4:$C$59=A18)*('📦 Inventario Maestro'!$O$4:$O$59)*('📦 Inventario Maestro'!$J$4:$J$59)) | G18: =F18-E18
A19: Periféricos y Accesorios | B19: =COUNTIF('📦 Inventario Maestro'!$C$4:$C$59, A19) | C19: =SUMIF('📦 Inventario Maestro'!$C$4:$C$59, A19, '📦 Inventario Maestro'!$J$4:$J$59) | D19: =SUMIF('📦 Inventario Maestro'!$C$4:$C$59, A19, '📦 Inventario Maestro'!$K$4:$K$59) | E19: =SUMPRODUCT(('📦 Inventario Maestro'!$C$4:$C$59=A19)*('📦 Inventario Maestro'!$M$4:$M$59)*('📦 Inventario Maestro'!$J$4:$J$59)) | F19: =SUMPRODUCT(('📦 Inventario Maestro'!$C$4:$C$59=A19)*('📦 Inventario Maestro'!$O$4:$O$59)*('📦 Inventario Maestro'!$J$4:$J$59)) | G19: =F19-E19
A20: Portátiles y Equipos | B20: =COUNTIF('📦 Inventario Maestro'!$C$4:$C$59, A20) | C20: =SUMIF('📦 Inventario Maestro'!$C$4:$C$59, A20, '📦 Inventario Maestro'!$J$4:$J$59) | D20: =SUMIF('📦 Inventario Maestro'!$C$4:$C$59, A20, '📦 Inventario Maestro'!$K$4:$K$59) | E20: =SUMPRODUCT(('📦 Inventario Maestro'!$C$4:$C$59=A20)*('📦 Inventario Maestro'!$M$4:$M$59)*('📦 Inventario Maestro'!$J$4:$J$59)) | F20: =SUMPRODUCT(('📦 Inventario Maestro'!$C$4:$C$59=A20)*('📦 Inventario Maestro'!$O$4:$O$59)*('📦 Inventario Maestro'!$J$4:$J$59)) | G20: =F20-E20
... A26: Tintas y Suministros | B26: =COUNTIF('📦 Inventario Maestro'!$C$4:$C$59, A26) | C26: =SUMIF('📦 Inventario Maestro'!$C$4:$C$59, A26, '📦 Inventario Maestro'!$J$4:$J$59) | D26: =SUMIF('📦 Inventario Maestro'!$C$4:$C$59, A26, '📦 Inventario Maestro'!$K$4:$K$59) | E26: =SUMPRODUCT(('📦 Inventario Maestro'!$C$4:$C$59=A26)*('📦 Inventario Maestro'!$M$4:$M$59)*('📦 Inventario Maestro'!$J$4:$J$59)) | F26: =SUMPRODUCT(('📦 Inventario Maestro'!$C$4:$C$59=A26)*('📦 Inventario Maestro'!$O$4:$O$59)*('📦 Inventario Maestro'!$J$4:$J$59)) | G26: =F26-E26
A27: TOTAL GENERAL | B27: =SUM(B9:B26) | C27: =SUM(C9:C26) | D27: =SUM(D9:D26) | E27: =SUM(E9:E26) | F27: =SUM(F9:F26) | G27: =SUM(G9:G26)

Sheet 🛠️ Triaje Usados y Repuestos
A1: MATRIZ DE TRIAJE 4T — EVALUACIÓN DE EQUIPOS USADOS Y REPUESTOS
A2: T1: Venta Inmediata (Listo) | T2: Reacondicionar (Inversión < 40% Venta) | T3: Banco Repuestos Taller | T4: Desecho / Reciclaje RAEE
A4: SKU Usado | B4: Equipo / Componente | C4: Marca / Modelo | D4: Código Barras / Serial | E4: Nivel Triaje (4T) | F4: Diagnóstico / Estado | G4: Acción Requerida | H4: Costo Inversión / Repuesto | I4: Precio Venta Estimado | J4: Utilidad Estimada | K4: Estado Actual | L4: Ubicación Taller | M4: Notas Técnicas
A5: MTS-U001 | B5: Portátil HP ProBook 450 G5 Core i5 8va Gen | C5: HP ProBook 450 G5 | D5: 5CD8124XYZ | E5: T1 - Venta Directa | F5: Estado estético 9/10, batería dura 2.5h, pantalla perfecta. | G5: Mantenimiento preventivo + pasta térmica nueva. | H5: 20000 | I5: 850000 | J5: =I5-H5 | K5: Listo para Venta | L5: Estante Usados - Nivel 1 | M5: Incluye cargador original HP. Se entrega con SSD 256GB y 16GB RAM.
A6: MTS-U002 | B6: Monitor LG 20" LED VGA/DVI | C6: LG 20M37A | D6: 504NDZK1234 | E6: T1 - Venta Directa | F6: Pantalla sin rayones ni pixeles muertos, incluye adaptador y cable VGA. | G6: Limpieza externa y prueba continua de 4 horas. | H6: 5000 | I6: 180000 | J6: =I6-H6 | K6: Listo para Venta | L6: Estante Usados - Nivel 2 | M6: Ideal para cámaras de seguridad, oficina o segundo monitor.
A7: MTS-U003 | B7: PC Torre Lenovo ThinkCentre M710s Core i5 | C7: Lenovo M710s SFF | D7: MJ05ABCD | E7: T2 - Reacondicionar | F7: Enciende bien, sin disco duro, requiere 8GB RAM adicionales. | G7: Instalar SSD Kingston 480GB nuevo + 8GB RAM DDR4. | H7: 150000 | I7: 650000 | J7: =I7-H7 | K7: En Proceso Taller | L7: Mesa de Trabajo 1 | M7: Costo reparación (23%) es muy rentable. Precio de mercado $650.000.
A8: MTS-R001 | B8: Pantalla 15.6" LED 30 Pines Slim FHD (Despiece) | C8: Dell Inspiron 3593 | D8: N/A | E8: T3 - Banco Repuestos | F8: Board con corto en procesador, display 100% operativo. | G8: Guardar en caja antiestática para cambios de display a clientes. | H8: 0 | I8: 220000 | J8: =I8-H8 | K8: En Stock Repuestos | L8: Caja Repuestos - Pantallas | M8: Ahorra comprar display nuevo de $280.000 en reparaciones.
A9: MTS-R002 | B9: Teclado Original Español Lenovo ThinkPad T480 | C9: Lenovo ThinkPad | D9: N/A | E9: T3 - Banco Repuestos | F9: Equipo donante con daño en board. Teclado en perfecto estado. | G9: Limpieza y prueba de todas las teclas. | H9: 0 | I9: 90000 | J9: =I9-H9 | K9: En Stock Repuestos | L9: Caja Repuestos - Teclados | M9: Repuesto genuino de alta rotación para clientes corporativos.
A10: MTS-D001 | B10: Carcasa rota + Board quemada Todo en Uno HP 20" | C10: HP All-in-One 20 | D10: N/A | E10: T4 - Desecho / RAEE | F10: Procesador integrado quemado, pantalla fisurada, carcasa partida. | G10: Extraer RAM DDR3L y disipador de cobre. Desechar el resto. | H10: 0 | I10: 0 | J10: 0 | K10: Para Descarte | L10: Caneca RAEE / Reciclaje | M10: Liberar espacio físico en el taller.

Sheet 💰 Calculadora de Precios
A1: CALCULADORA RÁPIDA DE PRECIOS POR CANAL — MAX TECHNOLOGY
A2: Escribe el costo de cualquier producto nuevo y el simulador calculará el precio exacto para cada canal.
A4: Costo de Compra Neto (con IVA si aplica): | B4: 150000 | D4: Flete o gastos adicionales: | E4: 5000
A5: Margen Neto Deseado (%): | B5: 0.3 | D5: Comisión MercadoLibre (%): | E5: 0.16
A6: Costo Flete Envío MercadoLibre (si aplica): | B6: 18000 | D6: Umbral Envío Gratis ML (COP): | E6: 90000
A8: Costo Total Producto: | B8: =B4+E4
A10: PRECIO RECOMENDADO WHATSAPP / DIRECTO: | B10: =ROUNDUP(B8/(1-B5), -3) | D10: Utilidad Neta Directa: | E10: =B10-B8
A11: PRECIO RECOMENDADO MERCADOLIBRE: | B11: =ROUNDUP((B8+IF(B10>=E6,B6,0))/(1-B5-E5), -3) | D11: Utilidad Neta MercadoLibre: | E11: =B11-(B8+IF(B10>=E6,B6,0))-(B11*E5)
A12: PRECIO RECOMENDADO FACEBOOK MARKETPLACE: | B12: =B10 | D12: Margen Real: | E12: =IF(B10>0,(B10-B8)/B10,0)
